Workbook

Sheet Mode d'emploi
A1: Rétroplanning type d'un événement — Pop Tables
A2: 28/10/2026 · 6 OPERATIONS/PRODUCTION · Document de travail du pôle Opérations : propositions, rien n'est décidé (voir REGISTRE DES DECISIONS).
A4: À quoi il sert
A5: À partir de la date de l'événement (J) et de son niveau de criticité (C1, C2, C3), il calcule la date de chaque jalon, son responsable et le process concerné (voir « 2026 1028 Fiches process PR-01 à PR-10 »). Il signale les jalons en retard et un délai de préparation insuffisant.
A7: Comment s'en servir
A8: 1. Dupliquer l'onglet « Événement (exemple) » pour chaque événement (clic droit sur l'onglet, puis Déplacer ou copier, en cochant Créer une copie).
A9: 2. Saisir uniquement les cellules jaunes : nom, date J, criticité. Le reste se calcule.
A10: 3. Mettre à jour la colonne Statut au fil de l'eau. Une ligne passe en rouge si sa date est dépassée sans être « Fait ».
A11: 4. Les décalages (en jours avant ou après J) se modifient dans l'onglet « Jalons ». Une case vide signifie que le jalon ne s'applique pas à ce niveau.
A13: Fondements
A14: Les jalons reprennent le plan des deux soirées pilotes du Produit (lieux et chefs à S-10, contrats à S-8, ventes à S-6, menu figé à S-3, seuil de confirmation à J-14, bilan à S+1), l'option de lancement du Marketing (invitation envoyée environ trois semaines avant) et les fiches process du pôle Opérations. Les autres décalages sont des propositions (P).
A15: Codes couleur : texte bleu sur fond jaune = saisie · texte noir = calcul · texte vert = lien vers un autre onglet · fond rouge = jalon en retard.
A16: L'exemple porte sur une date fictive (H) : aucune date de pilote n'est arrêtée.

Sheet Événement (exemple)
A1: Rétroplanning de l'événement
A3: Nom de l'événement | C3: Pilote 1 — Premier soir
A4: Date de l'événement (J) | C4: 46405
A5: Criticité (C1, C2, C3) | C5: C2
A7: Démarrage recommandé | C7: =IF(C5="","",C4-7*INDEX(Jalons!$E$31:$G$31,MATCH(C5,Jalons!$E$30:$G$30,0)))
A8: Alerte de délai | C8: =IF(C7="","",IF(TODAY()>C7,"Délai inférieur au délai recommandé : à arbitrer","Délai suffisant"))
A10: N° | B10: Jalon | C10: Process | D10: Responsable | E10: Décalage (jours) | F10: Date | G10: Jour | H10: Jours restants | I10: Statut | J10: Commentaire
A11: =Jalons!A5 | B11: =Jalons!B5 | C11: =Jalons!C5 | D11: =Jalons!D5 | E11: =IF($C$5="","",IF(INDEX(Jalons!$E5:$G5,MATCH($C$5,Jalons!$E$4:$G$4,0))="","",INDEX(Jalons!$E5:$G5,MATCH($C$5,Jalons!$E$4:$G$4,0)))) | F11: =IF(OR($C$4="",E11=""),"Sans objet",$C$4+E11) | G11: =IF(ISNUMBER(F11),CHOOSE(WEEKDAY(F11,2),"lundi","mardi","mercredi","jeudi","vendredi","samedi","dimanche"),"") | H11: =IF(ISNUMBER(F11),F11-TODAY(),"") | I11: À faire
A12: =Jalons!A6 | B12: =Jalons!B6 | C12: =Jalons!C6 | D12: =Jalons!D6 | E12: =IF($C$5="","",IF(INDEX(Jalons!$E6:$G6,MATCH($C$5,Jalons!$E$4:$G$4,0))="","",INDEX(Jalons!$E6:$G6,MATCH($C$5,Jalons!$E$4:$G$4,0)))) | F12: =IF(OR($C$4="",E12=""),"Sans objet",$C$4+E12) | G12: =IF(ISNUMBER(F12),CHOOSE(WEEKDAY(F12,2),"lundi","mardi","mercredi","jeudi","vendredi","samedi","dimanche"),"") | H12: =IF(ISNUMBER(F12),F12-TODAY(),"")
A13: =Jalons!A7 | B13: =Jalons!B7 | C13: =Jalons!C7 | D13: =Jalons!D7 | E13: =IF($C$5="","",IF(INDEX(Jalons!$E7:$G7,MATCH($C$5,Jalons!$E$4:$G$4,0))="","",INDEX(Jalons!$E7:$G7,MATCH($C$5,Jalons!$E$4:$G$4,0)))) | F13: =IF(OR($C$4="",E13=""),"Sans objet",$C$4+E13) | G13: =IF(ISNUMBER(F13),CHOOSE(WEEKDAY(F13,2),"lundi","mardi","mercredi","jeudi","vendredi","samedi","dimanche"),"") | H13: =IF(ISNUMBER(F13),F13-TODAY(),"")
A14: =Jalons!A8 | B14: =Jalons!B8 | C14: =Jalons!C8 | D14: =Jalons!D8 | E14: =IF($C$5="","",IF(INDEX(Jalons!$E8:$G8,MATCH($C$5,Jalons!$E$4:$G$4,0))="","",INDEX(Jalons!$E8:$G8,MATCH($C$5,Jalons!$E$4:$G$4,0)))) | F14: =IF(OR($C$4="",E14=""),"Sans objet",$C$4+E14) | G14: =IF(ISNUMBER(F14),CHOOSE(WEEKDAY(F14,2),"lundi","mardi","mercredi","jeudi","vendredi","samedi","dimanche"),"") | H14: =IF(ISNUMBER(F14),F14-TODAY(),"")
A15: =Jalons!A9 | B15: =Jalons!B9 | C15: =Jalons!C9 | D15: =Jalons!D9 | E15: =IF($C$5="","",IF(INDEX(Jalons!$E9:$G9,MATCH($C$5,Jalons!$E$4:$G$4,0))="","",INDEX(Jalons!$E9:$G9,MATCH($C$5,Jalons!$E$4:$G$4,0)))) | F15: =IF(OR($C$4="",E15=""),"Sans objet",$C$4+E15) | G15: =IF(ISNUMBER(F15),CHOOSE(WEEKDAY(F15,2),"lundi","mardi","mercredi","jeudi","vendredi","samedi","dimanche"),"") | H15: =IF(ISNUMBER(F15),F15-TODAY(),"")
A16: =Jalons!A10 | B16: =Jalons!B10 | C16: =Jalons!C10 | D16: =Jalons!D10 | E16: =IF($C$5="","",IF(INDEX(Jalons!$E10:$G10,MATCH($C$5,Jalons!$E$4:$G$4,0))="","",INDEX(Jalons!$E10:$G10,MATCH($C$5,Jalons!$E$4:$G$4,0)))) | F16: =IF(OR($C$4="",E16=""),"Sans objet",$C$4+E16) | G16: =IF(ISNUMBER(F16),CHOOSE(WEEKDAY(F16,2),"lundi","mardi","mercredi","jeudi","vendredi","samedi","dimanche"),"") | H16: =IF(ISNUMBER(F16),F16-TODAY(),"")
A17: =Jalons!A11 | B17: =Jalons!B11 | C17: =Jalons!C11 | D17: =Jalons!D11 | E17: =IF($C$5="","",IF(INDEX(Jalons!$E11:$G11,MATCH($C$5,Jalons!$E$4:$G$4,0))="","",INDEX(Jalons!$E11:$G11,MATCH($C$5,Jalons!$E$4:$G$4,0)))) | F17: =IF(OR($C$4="",E17=""),"Sans objet",$C$4+E17) | G17: =IF(ISNUMBER(F17),CHOOSE(WEEKDAY(F17,2),"lundi","mardi","mercredi","jeudi","vendredi","samedi","dimanche"),"") | H17: =IF(ISNUMBER(F17),F17-TODAY(),"")
A18: =Jalons!A12 | B18: =Jalons!B12 | C18: =Jalons!C12 | D18: =Jalons!D12 | E18: =IF($C$5="","",IF(INDEX(Jalons!$E12:$G12,MATCH($C$5,Jalons!$E$4:$G$4,0))="","",INDEX(Jalons!$E12:$G12,MATCH($C$5,Jalons!$E$4:$G$4,0)))) | F18: =IF(OR($C$4="",E18=""),"Sans objet",$C$4+E18) | G18: =IF(ISNUMBER(F18),CHOOSE(WEEKDAY(F18,2),"lundi","mardi","mercredi","jeudi","vendredi","samedi","dimanche"),"") | H18: =IF(ISNUMBER(F18),F18-TODAY(),"")
A19: =Jalons!A13 | B19: =Jalons!B13 | C19: =Jalons!C13 | D19: =Jalons!D13 | E19: =IF($C$5="","",IF(INDEX(Jalons!$E13:$G13,MATCH($C$5,Jalons!$E$4:$G$4,0))="","",INDEX(Jalons!$E13:$G13,MATCH($C$5,Jalons!$E$4:$G$4,0)))) | F19: =IF(OR($C$4="",E19=""),"Sans objet",$C$4+E19) | G19: =IF(ISNUMBER(F19),CHOOSE(WEEKDAY(F19,2),"lundi","mardi","mercredi","jeudi","vendredi","samedi","dimanche"),"") | H19: =IF(ISNUMBER(F19),F19-TODAY(),"")
A20: =Jalons!A14 | B20: =Jalons!B14 | C20: =Jalons!C14 | D20: =Jalons!D14 | E20: =IF($C$5="","",IF(INDEX(Jalons!$E14:$G14,MATCH($C$5,Jalons!$E$4:$G$4,0))="","",INDEX(Jalons!$E14:$G14,MATCH($C$5,Jalons!$E$4:$G$4,0)))) | F20: =IF(OR($C$4="",E20=""),"Sans objet",$C$4+E20) | G20: =IF(ISNUMBER(F20),CHOOSE(WEEKDAY(F20,2),"lundi","mardi","mercredi","jeudi","vendredi","samedi","dimanche"),"") | H20: =IF(ISNUMBER(F20),F20-TODAY(),"")
A21: =Jalons!A15 | B21: =Jalons!B15 | C21: =Jalons!C15 | D21: =Jalons!D15 | E21: =IF($C$5="","",IF(INDEX(Jalons!$E15:$G15,MATCH($C$5,Jalons!$E$4:$G$4,0))="","",INDEX(Jalons!$E15:$G15,MATCH($C$5,Jalons!$E$4:$G$4,0)))) | F21: =IF(OR($C$4="",E21=""),"Sans objet",$C$4+E21) | G21: =IF(ISNUMBER(F21),CHOOSE(WEEKDAY(F21,2),"lundi","mardi","mercredi","jeudi","vendredi","samedi","dimanche"),"") | H21: =IF(ISNUMBER(F21),F21-TODAY(),"")
A22: =Jalons!A16 | B22: =Jalons!B16 | C22: =Jalons!C16 | D22: =Jalons!D16 | E22: =IF($C$5="","",IF(INDEX(Jalons!$E16:$G16,MATCH($C$5,Jalons!$E$4:$G$4,0))="","",INDEX(Jalons!$E16:$G16,MATCH($C$5,Jalons!$E$4:$G$4,0)))) | F22: =IF(OR($C$4="",E22=""),"Sans objet",$C$4+E22) | G22: =IF(ISNUMBER(F22),CHOOSE(WEEKDAY(F22,2),"lundi","mardi","mercredi","jeudi","vendredi","samedi","dimanche"),"") | H22: =IF(ISNUMBER(F22),F22-TODAY(),"")
A23: =Jalons!A17 | B23: =Jalons!B17 | C23: =Jalons!C17 | D23: =Jalons!D17 | E23: =IF($C$5="","",IF(INDEX(Jalons!$E17:$G17,MATCH($C$5,Jalons!$E$4:$G$4,0))="","",INDEX(Jalons!$E17:$G17,MATCH($C$5,Jalons!$E$4:$G$4,0)))) | F23: =IF(OR($C$4="",E23=""),"Sans objet",$C$4+E23) | G23: =IF(ISNUMBER(F23),CHOOSE(WEEKDAY(F23,2),"lundi","mardi","mercredi","jeudi","vendredi","samedi","dimanche"),"") | H23: =IF(ISNUMBER(F23),F23-TODAY(),"")
... A34: =Jalons!A28 | B34: =Jalons!B28 | C34: =Jalons!C28 | D34: =Jalons!D28 | E34: =IF($C$5="","",IF(INDEX(Jalons!$E28:$G28,MATCH($C$5,Jalons!$E$4:$G$4,0))="","",INDEX(Jalons!$E28:$G28,MATCH($C$5,Jalons!$E$4:$G$4,0)))) | F34: =IF(OR($C$4="",E34=""),"Sans objet",$C$4+E34) | G34: =IF(ISNUMBER(F34),CHOOSE(WEEKDAY(F34,2),"lundi","mardi","mercredi","jeudi","vendredi","samedi","dimanche"),"") | H34: =IF(ISNUMBER(F34),F34-TODAY(),"")

Sheet Jalons
A1: Jalons et décalages par niveau de criticité
A2: Décalage en jours par rapport au jour J (négatif = avant). Case vide = sans objet à ce niveau. Cellules jaunes modifiables.
A4: N° | B4: Jalon | C4: Process | D4: Responsable | E4: C1 | F4: C2 | G4: C3 | H4: Nature | I4: Fondement
A5: 1 | B5: Ouverture du dossier, catégorie fixée, fiche technique v1 | C5: PR-03 | D5: Opérations | E5: -56 | F5: -70 | G5: -84 | H5: P / F | I5: Plan des pilotes du Produit : lieux et chefs à S-10 (C2) ; C1 : 2 semaines avant les ventes ; C3 : 2 semaines de plus
A6: 2 | B6: Lieu qualifié (fiche du lieu) | C6: PR-01 | D6: Ventes + Opérations | E6: -56 | F6: -70 | G6: -84 | H6: P / F | I6: Plan des pilotes du Produit : S-10
A7: 3 | B7: Chef engagé, chef de secours identifié | C7: PR-02 | D7: Ventes + Opérations | E7: -56 | F7: -70 | G7: -84 | H7: P / F | I7: Plan des pilotes du Produit : S-10
A8: 4 | B8: Devis de staffing et de fournisseurs reçus | C8: PR-04, PR-05 | D8: Opérations | E8: -49 | F8: -63 | G8: -70 | H8: P
A9: 5 | B9: Contrats du lieu et du chef signés ; assurance ; licence de Pop Tables déclarée (D-09) avant toute commande de vin ; contrat M04 avec AdVini signé ; plan de maîtrise sanitaire en place | C9: PR-02 | D9: Juridique | E9: -49 | F9: -56 | G9: -63 | H9: P / F | I9: Plan des pilotes du Produit : contrats à S-8, signés avant l'ouverture des ventes
A10: 6 | B10: Budget réel validé | C10: PR-10 | D10: Finance | E10: -45 | F10: -49 | G10: -56 | H10: P
A11: 7 | B11: Ouverture des ventes (offre A) ou signature du client (offre B) | C11: — | D11: Marketing / Ventes | E11: -42 | F11: -42 | G11: -42 | H11: F | I11: Plan des pilotes du Produit : ventes à S-6
A12: 8 | B12: Produits rares ou importés commandés | C12: PR-05 | D12: Opérations | F12: -35 | G12: -42 | H12: P
A13: 9 | B13: Menu et accords figés, fiche technique v2 | C13: PR-03 | D13: Chef + Opérations | E13: -21 | F13: -21 | G13: -28 | H13: F / P | I13: Plan des pilotes du Produit : S-3
A14: 10 | B14: Dégustation du menu | C14: PR-07 | D14: Chef + Direction | G14: -21 | H14: P
A15: 11 | B15: Invitations envoyées (soirée signature) | C15: — | D15: Marketing | G15: -21 | H15: F | I15: Premier événement, Marketing : invitation envoyée environ trois semaines avant
A16: 12 | B16: Équipe réservée | C16: PR-04 | D16: Opérations | E16: -21 | F16: -21 | G16: -28 | H16: P
A17: 13 | B17: Seuil de confirmation (offre A) : environ 70 % des sièges vendus | C17: — | D17: Produit + Finance | E17: -14 | F17: -14 | G17: -14 | H17: F | I17: Plan des pilotes du Produit : J-14
A18: 14 | B18: Liste des convives, allergies, plan de table | C18: PR-06 | D18: Opérations | E18: -7 | F18: -7 | G18: -10 | H18: P
A19: 15 | B19: Produits frais commandés ; matériel et transport confirmés | C19: PR-05 | D19: Opérations | E19: -7 | F19: -7 | G19: -10 | H19: P
A20: 16 | B20: Fiche technique finale diffusée à l'équipe | C20: PR-03 | D20: Opérations | E20: -3 | F20: -3 | G20: -5 | H20: P
A21: 17 | B21: Confirmation de chaque intervenant | C21: PR-04 | D21: Opérations | E21: -2 | F21: -2 | G21: -2 | H21: P
A22: 18 | B22: Répétition sur place | C22: PR-07 | D22: Opérations | G22: -2 | H22: P
A23: 19 | B23: Arrivée du chef venu de loin ; réception des produits | C23: PR-02, PR-05 | D23: Opérations | E23: -1 | F23: -1 | G23: -1 | H23: P
A24: 20 | B24: Jour J | C24: PR-07 | D24: Tous | E24: 0 | F24: 0 | G24: 0 | H24: —
A25: 21 | B25: Restitution du lieu, état des lieux de sortie (avant réouverture) | C25: PR-08 | D25: Opérations | E25: 0 | F25: 0 | G25: 0 | H25: P
A26: 22 | B26: Questionnaire de satisfaction ; retours du chef, du lieu et de l'équipe | C26: PR-10 | D26: Opérations | E26: 1 | F26: 1 | G26: 1 | H26: F | I26: Plan des pilotes du Produit : questionnaire envoyé le lendemain
A27: 23 | B27: Bilan chiffré : coût réel et coût prévu | C27: PR-10 | D27: Opérations + Finance | E27: 7 | F27: 7 | G27: 7 | H27: F | I27: Plan des pilotes du Produit : bilan à S+1
A28: 24 | B28: Notation des prestataires ; mise à jour du calculateur de staffing | C28: PR-10 | D28: Opérations | E28: 7 | F28: 7 | G28: 7 | H28: P
A30: Démarrage recommandé (semaines avant J) | D30: Niveau | E30: C1 | F30: C2 | G30: C3
D31: Semaines | E31: =-MIN(E5:E28)/7 | F31: =-MIN(F5:F28)/7 | G31: =-MIN(G5:G28)/7
