Workbook

Sheet Lisez-moi
A1: Pop Tables — Prescripteurs à Paris pour toucher les foodies et la clientèle BtoC premium
A2: Pôle Ventes · 28/10/2026 · Document de travail, non validé
A4: Ce qu'est un prescripteur ici
A5: Une organisation qui recommande ou revend nos soirées à ses propres clients ou membres : elle ne paie pas, elle apporte des convives. Cible : places à l'unité en drop (B2C) et privatisations de groupes constitués (cadre Pop Tables, D-04).
A7: Code couleur
A8: Ligne blanche : conciergerie de luxe (ta demande).
A9: Ligne BLEUE : autre prescripteur que j'ai identifié (concierges d'hôtels, cartes premium, agences de voyage, médias, family offices, caves).
A10: ORANGE : inférence ou proposition de l'assistant IA (pourquoi ce prescripteur, contrepartie envisageable).
A11: JAUNE : colonnes de suivi.
A13: Précautions
A14: • Les comparatifs de conciergeries sont des sites commerciaux : classements et chiffres annoncés sont des argumentaires, à vérifier en rendez-vous.
A15: • Aucune commission ni exclusivité ne se promet avant validation (Finance, Direction) ; aucun prix public (D-11) : le prix se donne au moment de la réservation.
... A17: • Hautes Expériences est un concurrent-partenaire : ne pas lui transmettre l'offre avant d'avoir étudié la complémentarité.

Sheet Synthèse
A1: Prescripteurs : synthèse par famille
A3: Famille | B3: Type | C3: Lignes | D3: Priorité A | E3: Priorité B | F3: Priorité C
A4: 1. Conciergeries lifestyle à Paris | B4: Conciergerie de luxe | C4: =COUNTIF(Prescripteurs!$C$2:$C$34,A4) | D4: =COUNTIFS(Prescripteurs!$C$2:$C$34,A4,Prescripteurs!$J$2:$J$34,"A") | E4: =COUNTIFS(Prescripteurs!$C$2:$C$34,A4,Prescripteurs!$J$2:$J$34,"B") | F4: =COUNTIFS(Prescripteurs!$C$2:$C$34,A4,Prescripteurs!$J$2:$J$34,"C")
A5: 2. Conciergeries de réseau / entreprise | B5: Conciergerie de luxe | C5: =COUNTIF(Prescripteurs!$C$2:$C$34,A5) | D5: =COUNTIFS(Prescripteurs!$C$2:$C$34,A5,Prescripteurs!$J$2:$J$34,"A") | E5: =COUNTIFS(Prescripteurs!$C$2:$C$34,A5,Prescripteurs!$J$2:$J$34,"B") | F5: =COUNTIFS(Prescripteurs!$C$2:$C$34,A5,Prescripteurs!$J$2:$J$34,"C")
A6: 3. Concierges d'hôtels et palaces | B6: Autre prescripteur | C6: =COUNTIF(Prescripteurs!$C$2:$C$34,A6) | D6: =COUNTIFS(Prescripteurs!$C$2:$C$34,A6,Prescripteurs!$J$2:$J$34,"A") | E6: =COUNTIFS(Prescripteurs!$C$2:$C$34,A6,Prescripteurs!$J$2:$J$34,"B") | F6: =COUNTIFS(Prescripteurs!$C$2:$C$34,A6,Prescripteurs!$J$2:$J$34,"C")
A7: 4. Cartes bancaires premium | B7: Autre prescripteur | C7: =COUNTIF(Prescripteurs!$C$2:$C$34,A7) | D7: =COUNTIFS(Prescripteurs!$C$2:$C$34,A7,Prescripteurs!$J$2:$J$34,"A") | E7: =COUNTIFS(Prescripteurs!$C$2:$C$34,A7,Prescripteurs!$J$2:$J$34,"B") | F7: =COUNTIFS(Prescripteurs!$C$2:$C$34,A7,Prescripteurs!$J$2:$J$34,"C")
A8: 5. Agences de voyage de luxe et DMC | B8: Autre prescripteur | C8: =COUNTIF(Prescripteurs!$C$2:$C$34,A8) | D8: =COUNTIFS(Prescripteurs!$C$2:$C$34,A8,Prescripteurs!$J$2:$J$34,"A") | E8: =COUNTIFS(Prescripteurs!$C$2:$C$34,A8,Prescripteurs!$J$2:$J$34,"B") | F8: =COUNTIFS(Prescripteurs!$C$2:$C$34,A8,Prescripteurs!$J$2:$J$34,"C")
A9: 6. Médias, guides et influence food | B9: Autre prescripteur | C9: =COUNTIF(Prescripteurs!$C$2:$C$34,A9) | D9: =COUNTIFS(Prescripteurs!$C$2:$C$34,A9,Prescripteurs!$J$2:$J$34,"A") | E9: =COUNTIFS(Prescripteurs!$C$2:$C$34,A9,Prescripteurs!$J$2:$J$34,"B") | F9: =COUNTIFS(Prescripteurs!$C$2:$C$34,A9,Prescripteurs!$J$2:$J$34,"C")
A10: 7. Gestion de fortune et family offices | B10: Autre prescripteur | C10: =COUNTIF(Prescripteurs!$C$2:$C$34,A10) | D10: =COUNTIFS(Prescripteurs!$C$2:$C$34,A10,Prescripteurs!$J$2:$J$34,"A") | E10: =COUNTIFS(Prescripteurs!$C$2:$C$34,A10,Prescripteurs!$J$2:$J$34,"B") | F10: =COUNTIFS(Prescripteurs!$C$2:$C$34,A10,Prescripteurs!$J$2:$J$34,"C")
A11: 8. Caves et écoles de dégustation | B11: Autre prescripteur | C11: =COUNTIF(Prescripteurs!$C$2:$C$34,A11) | D11: =COUNTIFS(Prescripteurs!$C$2:$C$34,A11,Prescripteurs!$J$2:$J$34,"A") | E11: =COUNTIFS(Prescripteurs!$C$2:$C$34,A11,Prescripteurs!$J$2:$J$34,"B") | F11: =COUNTIFS(Prescripteurs!$C$2:$C$34,A11,Prescripteurs!$J$2:$J$34,"C")
A12: Total | C12: =SUM(C4:C11) | D12: =SUM(D4:D11) | E12: =SUM(E4:E11) | F12: =SUM(F4:F11)

Sheet Prescripteurs
A1: ID | B1: Type | C1: Famille | D1: Organisation | E1: Ce qu'ils font (faits publics) | F1: Clientèle relayée | G1: Pourquoi pour Pop Tables (inférence) | H1: Contrepartie envisageable (proposition) | I1: Interlocuteur visé (rôle) | J1: Priorité | K1: Fiabilité de la source | L1: Sources | M1: Statut | N1: Date dernier contact | O1: Prochaine action | P1: Responsable | Q1: Commentaires
A2: PR01 | B2: Conciergerie de luxe | C2: 1. Conciergeries lifestyle à Paris | D2: Premium Conciergerie | E2: Conciergerie privée 24h/24 (SAS créée en 2015, 10 à 19 salariés) ; formule privée affichée à 6 000 € HT par an ; 20 concierges et 6 000 partenaires annoncés. | F2: BtoC premium, dirigeants | G2: Clientèle qui paie déjà pour l'accès à l'introuvable. | H2: Commission par place ou par privatisation | I2: Directeur·rice des partenariats | J2: A | K2: Comparatif commercial | L2: S1, S2 | M2: À qualifier | O2: Identifier l'interlocuteur
A3: PR02 | B3: Conciergerie de luxe | C3: 1. Conciergeries lifestyle à Paris | D3: Unique Paris | E3: Conciergerie sur adhésion pour dirigeants, banquiers, consultants et gérants de fonds. | F3: BtoC premium, dirigeants | G3: Profil exact des acheteurs de privatisations. | H3: Commission ; accès prioritaire aux drops | I3: Fondateur·rice / partenariats | J3: A | K3: Comparatif commercial | L3: S1 | M3: À qualifier | O3: Identifier l'interlocuteur
A4: PR03 | B4: Conciergerie de luxe | C4: 1. Conciergeries lifestyle à Paris | D4: Joie Paris | E4: Conciergerie fondée en 2019, citée par Forbes comme meilleure conciergerie de Paris en 2023 (selon le comparatif). | F4: BtoC premium, international | G4: Clientèle internationale en quête d'expériences parisiennes rares. | H4: Commission | I4: Fondateur·rice | J4: A | K4: Comparatif commercial | L4: S1 | M4: À qualifier | O4: Identifier l'interlocuteur
A5: PR04 | B5: Conciergerie de luxe | C5: 1. Conciergeries lifestyle à Paris | D5: Louis Prestige | E5: Conciergerie privée à trois niveaux d'abonnement (Bronze, Gold, Diamond), Paris 16e. | F5: BtoC premium | G5: Abonnés haut de gamme. | H5: Commission | I5: Fondateur | J5: B | K5: Comparatif commercial | L5: S1 | M5: À qualifier | O5: Identifier l'interlocuteur
A6: PR05 | B6: Conciergerie de luxe | C6: 1. Conciergeries lifestyle à Paris | D6: Séjour Privé | E6: Organisateur de séjours de luxe plus que conciergerie (selon le comparatif). | F6: International | G6: Clients de passage à Paris : soirée unique pendant le séjour. | H6: Commission | I6: Direction commerciale | J6: B | K6: Comparatif commercial | L6: S1 | M6: À qualifier | O6: Identifier l'interlocuteur
A7: PR06 | B7: Conciergerie de luxe | C7: 1. Conciergeries lifestyle à Paris | D7: Montaigne Conciergerie | E7: Conciergerie orientée mode et shopping, 42 avenue Montaigne (8e). | F7: BtoC premium, international | G7: Clientèle luxe de l'avenue Montaigne. | H7: Commission | I7: Direction | J7: B | K7: Comparatif commercial | L7: S1 | M7: À qualifier | O7: Identifier l'interlocuteur
A8: PR07 | B8: Conciergerie de luxe | C8: 1. Conciergeries lifestyle à Paris | D8: Le Collectionist ; The Lander | E8: Location de logements haut de gamme avec service de conciergerie. | F8: International, familles | G8: Clients logés dans des appartements de prestige à Paris. | H8: Commission | I8: Responsable conciergerie Paris | J8: B | K8: Comparatif commercial | L8: S1 | M8: À qualifier | O8: Identifier l'interlocuteur
A9: PR08 | B9: Conciergerie de luxe | C9: 1. Conciergeries lifestyle à Paris | D9: Mister Concierge, Art de Vie, Avant-Garde Conciergerie, RH Conciergerie Privée | E9: Autres conciergeries de luxe citées par les comparatifs 2026. | F9: BtoC premium | G9: À qualifier une par une. | H9: Commission | I9: Direction | J9: C | K9: Comparatif commercial | L9: S1, S3 | M9: À qualifier | O9: Identifier l'interlocuteur
A10: PR09 | B10: Conciergerie de luxe | C10: 1. Conciergeries lifestyle à Paris | D10: Jani Properties Conciergerie | E10: Service parisien pour clientèle VIP : transport privé, hébergement, événementiel. | F10: International | G10: Relais VIP. | H10: Commission | I10: Direction | J10: C | K10: Site / annonce | L10: S4 | M10: À qualifier | O10: Identifier l'interlocuteur
A11: PR10 | B11: Conciergerie de luxe | C11: 2. Conciergeries de réseau / entreprise | D11: John Paul (groupe Accor) | E11: Conciergerie premium : recrute des « concierges premium » à Paris ; programmes de fidélisation pour marques et entreprises. | F11: BtoC premium via marques, BtoB | G11: Gère les programmes de clients premium de grandes marques. | H11: Référencement dans le catalogue d'expériences | I11: Responsable des partenariats | J11: A | K11: Offres d'emploi (Journal des Palaces) | L11: S5 | M11: À qualifier | O11: Identifier l'interlocuteur
A12: PR11 | B12: Conciergerie de luxe | C12: 2. Conciergeries de réseau / entreprise | D12: Quintessentially | E12: Conciergerie internationale sur adhésion (citée sur des forums de voyageurs ; présence parisienne à vérifier). | F12: International, BtoC premium | G12: Membres ultra-premium. | H12: Commission | I12: Responsable des partenariats | J12: A | K12: Forum (anecdotique) | L12: S6 | M12: À qualifier | O12: Identifier l'interlocuteur
A13: PR12 | B13: Conciergerie de luxe | C13: 2. Conciergeries de réseau / entreprise | D13: Ten Lifestyle Group ; Generali Concierge Services | E13: Conciergeries pour banques et assureurs (Generali cité dans des offres d'emploi parisiennes ; Ten à vérifier). | F13: Porteurs de cartes, clients d'assureurs | G13: Accès indirect à des milliers de clients premium. | H13: Référencement | I13: Responsable de l'offre expériences | J13: B | K13: Offres d'emploi | L13: S5 | M13: À qualifier | O13: Identifier l'interlocuteur
... A34: PR33 | B34: Autre prescripteur | C34: 8. Caves et écoles de dégustation | D34: Grands cavistes parisiens (Legrand Filles et Fils, Lavinia, Caves Taillevent) | E34: Proposition : caves de référence avec une clientèle d'amateurs ; programmes d'événements non vérifiés. | F34: Foodies, amateurs de vin | G34: Relais naturel pour le « troisième inaccessible : la cave ». | H34: Partenariat vins ; places pour leurs clients | I34: Responsable événements | J34: B | K34: Proposition (non vérifié) | L34: — | M34: À qualifier | O34: Identifier l'interlocuteur

Sheet Sources
A1: Réf. | B1: Source | C1: Lien | D1: Date
A2: S1 | B2: Allovoyages, conciergerie de luxe Paris : 10 services comparés | C2: https://allovoyages.fr/a-la-une/conciergerie-de-luxe-paris/ | D2: 2026
A3: S2 | B3: Les meilleures conciergeries, top 10 conciergeries de luxe Paris | C3: https://les-meilleures-conciergeries.fr/meilleures-conciergeries-luxe-paris/ | D3: 2026
A4: S3 | B4: Conciergeries-luxe.fr, Paris | C4: https://www.conciergeries-luxe.fr/villes/paris | D4: 2026
A5: S4 | B5: Intermedialab, top 5 des conciergeries de luxe à Paris en 2026 | C5: https://www.intermedialab.eu/top-5-des-conciergeries-de-luxe-a-paris-en-2026/ | D5: 2026
A6: S5 | B6: Journal des Palaces, offre Concierge Premium John Paul Paris | C6: https://www.journaldespalaces.com/carriere/offre-306182-Concierge-Premium-Profil-Agent-de-voyage--John-Paul-Paris.html | D6: 2026
A7: S6 | B7: FlyerTalk, best hotel concierge in Paris (forum) | C7: https://www.flyertalk.com/forum/showthread.php?p=19793234 | D7: non datée
A8: S7 | B8: Journal du Luxe, record de Clefs d'Or dans un palace parisien | C8: https://www.journalduluxe.fr/fr/lifestyle/ce-palace-parisien-decroche-un-nombre-record-de-clefs-d-or/amp | D8: non datée
A9: S8 | B9: Journal des Palaces, élection à la tête des Clefs d'Or France (420 adhérents) | C9: https://www.journaldespalaces.com/communique-28479-elections-de-monsieur-lionel-lorans-a-la-tete-des-clefs-d-or-france.html | D9: ancienne
A10: S9 | B10: Journal des Palaces, une nouvelle génération de concierges reçoit les Clefs d'Or | C10: https://www.journaldespalaces.com/article-78177-nnvn-nement-une-nouvelle-gn-nn-ration-de-concierges-embarque-avec-les-clefs-d-or.html | D10: mai 2026
A11: S10 | B11: Journal des Palaces, le Chairman's Club du Forbes Travel Guide signe une première parisienne | C11: https://www.journaldespalaces.com/article-75735-evenements-le-chairman-s-club-du-forbes-travel-guide-signe-une-premiere-parisienne.html | D11: août 2025
A12: S11 | B12: Selectra, American Express Centurion en bref | C12: https://selectra.info/finance/banques/american-express/centurion | D12: 2026
... A31: S30 | B31: Groupon, Grains Nobles Paris 5e | C31: https://www.groupon.fr/biz/paris/grains-nobles-5eme | D31: non datée
