Workbook

Sheet Lisez-moi
A1: Pop Tables — Vivier de chefs potentiels à Paris (passés par l'étoilé ou indépendants reconnus)
A2: Pôle Ventes · 28/10/2026 · Document de travail, non validé · à transmettre au pôle Produit
A4: À lire d'abord
A5: La sélection des chefs relève du pôle Produit (décision D-18 du 28/10/2026). Ce fichier est un vivier proposé par les Ventes : il ne vaut ni choix, ni contact.
A7: Code couleur
A8: VERT : fait public, daté et sourcé (colonne Sources, onglet Sources).
A9: ORANGE : inférence de l'assistant IA (disponibilité probable, intérêt pour Pop Tables), à vérifier.
A10: JAUNE : colonnes de suivi à remplir par l'équipe.
A12: Priorités (proposition)
A13: A = profil le plus proche du cadre Pop Tables (chef rare ou sans table à Paris, habitué de l'éphémère) et disponibilité probable. B = intéressant, disponibilité à négocier. C = grand nom en poste : soirée exceptionnelle ou à quatre mains seulement.
A15: Précautions
A16: • Informations professionnelles publiques uniquement ; aucune coordonnée personnelle. Approche par le restaurant, le compte professionnel ou l'agent.
... A19: • Les chefs de la catégorie 6 sont en poste dans des restaurants récemment distingués : ils sont accessibles à Paris, donc moins « rares » au sens de la philosophie du projet.

Sheet Synthèse
A1: Vivier de chefs : synthèse
A3: Catégorie | B3: Chefs | C3: Priorité A | D3: Priorité B | E3: Priorité C
A4: 1. Chef étoilé en transition | B4: =COUNTIF(Chefs!$C$2:$C$29,A4) | C4: =COUNTIFS(Chefs!$C$2:$C$29,A4,Chefs!$J$2:$J$29,"A") | D4: =COUNTIFS(Chefs!$C$2:$C$29,A4,Chefs!$J$2:$J$29,"B") | E4: =COUNTIFS(Chefs!$C$2:$C$29,A4,Chefs!$J$2:$J$29,"C")
A5: 2. Chef étoilé hors Paris, déjà venu en pop-up | B5: =COUNTIF(Chefs!$C$2:$C$29,A5) | C5: =COUNTIFS(Chefs!$C$2:$C$29,A5,Chefs!$J$2:$J$29,"A") | D5: =COUNTIFS(Chefs!$C$2:$C$29,A5,Chefs!$J$2:$J$29,"B") | E5: =COUNTIFS(Chefs!$C$2:$C$29,A5,Chefs!$J$2:$J$29,"C")
A6: 3. Chef indépendant / pop-up / supper club | B6: =COUNTIF(Chefs!$C$2:$C$29,A6) | C6: =COUNTIFS(Chefs!$C$2:$C$29,A6,Chefs!$J$2:$J$29,"A") | D6: =COUNTIFS(Chefs!$C$2:$C$29,A6,Chefs!$J$2:$J$29,"B") | E6: =COUNTIFS(Chefs!$C$2:$C$29,A6,Chefs!$J$2:$J$29,"C")
A7: 4. Second ou ancien d'une maison étoilée | B7: =COUNTIF(Chefs!$C$2:$C$29,A7) | C7: =COUNTIFS(Chefs!$C$2:$C$29,A7,Chefs!$J$2:$J$29,"A") | D7: =COUNTIFS(Chefs!$C$2:$C$29,A7,Chefs!$J$2:$J$29,"B") | E7: =COUNTIFS(Chefs!$C$2:$C$29,A7,Chefs!$J$2:$J$29,"C")
A8: 5. Chef privé passé par l'étoilé | B8: =COUNTIF(Chefs!$C$2:$C$29,A8) | C8: =COUNTIFS(Chefs!$C$2:$C$29,A8,Chefs!$J$2:$J$29,"A") | D8: =COUNTIFS(Chefs!$C$2:$C$29,A8,Chefs!$J$2:$J$29,"B") | E8: =COUNTIFS(Chefs!$C$2:$C$29,A8,Chefs!$J$2:$J$29,"C")
A9: 6. Nouveau talent distingué en 2026 (en poste) | B9: =COUNTIF(Chefs!$C$2:$C$29,A9) | C9: =COUNTIFS(Chefs!$C$2:$C$29,A9,Chefs!$J$2:$J$29,"A") | D9: =COUNTIFS(Chefs!$C$2:$C$29,A9,Chefs!$J$2:$J$29,"B") | E9: =COUNTIFS(Chefs!$C$2:$C$29,A9,Chefs!$J$2:$J$29,"C")
A10: 7. Meilleur Ouvrier de France | B10: =COUNTIF(Chefs!$C$2:$C$29,A10) | C10: =COUNTIFS(Chefs!$C$2:$C$29,A10,Chefs!$J$2:$J$29,"A") | D10: =COUNTIFS(Chefs!$C$2:$C$29,A10,Chefs!$J$2:$J$29,"B") | E10: =COUNTIFS(Chefs!$C$2:$C$29,A10,Chefs!$J$2:$J$29,"C")
A11: Total | B11: =SUM(B4:B10) | C11: =SUM(C4:C10) | D11: =SUM(D4:D10) | E11: =SUM(E4:E10)

Sheet Chefs
A1: ID | B1: Chef | C1: Catégorie | D1: Cuisine | E1: Parcours et faits publics (datés) | F1: Situation connue | G1: Disponibilité probable (inférence) | H1: Pourquoi pour Pop Tables (inférence) | I1: Canal d'approche | J1: Priorité | K1: À vérifier | L1: Sources | M1: Statut | N1: Date dernier contact | O1: Prochaine action | P1: Responsable | Q1: Commentaires
A2: CH01 | B2: Boris Campanella | C2: 1. Chef étoilé en transition | D2: Gastronomie française de palace | E2: Chef exécutif et directeur de la gastronomie de l'Hôtel de Crillon pendant 8 ans ; L'Écrin (4 toques Gault&Millau, étoilé) fermé le 31/12/2025. | F2: A quitté le Crillon le 31/12/2025 ; prochaine destination non annoncée. | G2: Probablement disponible pour des soirées ponctuelles pendant sa transition. | H2: Signature de palace sans adresse actuelle : exactement « le chef qu'on ne peut plus réserver ». | I2: Réseau professionnel / LinkedIn | J2: A | K2: Nouveau poste éventuel depuis janvier 2026 | L2: S1, S2 | M2: À qualifier | O2: Vérifier la situation actuelle
A3: CH02 | B3: Adeline Grattard | C3: 1. Chef étoilé en transition | D3: Franco-chinoise, accords thé | E3: Yam'Tcha (1 étoile, rue Saint-Honoré) fermé le 20/12/2025 ; garde la boutique rue Sauval ; bistrot Yam'Tcha annoncé pour mars 2026. | F3: Restaurant étoilé fermé ; bistrot annoncé (ouverture non confirmée). | G3: Disponible pour des dîners d'exception si le bistrot lui laisse des soirs. | H3: Cuisine rare à Paris, notoriété forte : fidèles de Yam'Tcha sans table étoilée. | I3: Via la boutique Yam'Tcha / compte professionnel | J3: A | K3: Ouverture effective du bistrot | L3: S3 | M3: À qualifier | O3: Vérifier la situation actuelle
A4: CH03 | B4: Florent Pietravalle | C4: 2. Chef étoilé hors Paris, déjà venu en pop-up | D4: Provençale gastronomique | E4: Chef étoilé de La Mirande (Avignon) ; premier pop-up en France au Mandarin Oriental Lutetia, 19/06–19/07/2025, du jeudi au samedi. | F4: En poste à Avignon. | G4: Déjà rodé au pop-up parisien ; disponibilité à négocier. | H4: Chef étoilé absent de Paris : cœur de la philosophie Pop Tables. | I4: Via La Mirande ou l'équipe du Lutetia | J4: A | K4: Calendrier 2027 | L4: S7, S8 | M4: À qualifier | O4: Vérifier la situation actuelle
A5: CH04 | B5: Alexandre Gauthier | C5: 2. Chef étoilé hors Paris, déjà venu en pop-up | D5: Gastronomie d'auteur (Côte d'Opale) | E5: Chef de La Grenouillère ; restaurant éphémère à Paris dans un lieu secret en avril 2024, dîner à 520 € par personne. | F5: En poste à La Grenouillère. | G5: A déjà fait l'éphémère parisien à un prix très élevé. | H5: Preuve qu'une clientèle paie 500 € pour un grand chef de passage. | I5: Via La Grenouillère | J5: A | K5: Envie de renouveler | L5: S9 | M5: À qualifier | O5: Vérifier la situation actuelle
A6: CH05 | B6: Alexy Algar-Denos | C6: 3. Chef indépendant / pop-up / supper club | D6: Cuisine d'auteur | E6: Finaliste de Top Chef 2026 (protégé de Glenn Viel) ; pop-up Cramat' à Saint-Cloud jusqu'à fin septembre 2026 ; Cramat' Paris 9 annoncé. | F6: Chef de pop-up. | G6: Format éphémère déjà pratiqué. | H6: Notoriété récente + habitude du pop-up. | I6: Compte professionnel Cramat' | J6: A | K6: Dates de Cramat' Paris 9 | L6: S10, S11 | M6: À qualifier | O6: Vérifier la situation actuelle
A7: CH06 | B7: Jesús Durón | C7: 3. Chef indépendant / pop-up / supper club | D7: Mexicaine contemporaine | E7: Chef invité de la résidence Fulgurances (Paris 11e), 22/07–10/08/2024 ; menus pour une table éphémère de We Are Ona pendant Art Basel Paris. | F7: Chef de résidences et de pop-up. | G7: Habitué des formats éphémères. | H7: Grand chef étranger : correspond à l'exemple « soirée mexicaine » du projet. | I7: Via Fulgurances | J7: A | K7: Présence à Paris | L7: S12, S13 | M7: À qualifier | O7: Vérifier la situation actuelle
A8: CH07 | B8: Dalad Kambhu | C8: 3. Chef indépendant / pop-up / supper club | D8: Thaïlandaise | E8: Table éphémère « Dalad's » avec l'artiste Rirkrit Tiravanija pendant Art Basel Paris, 18–25/10/2026. | F8: Cheffe de table éphémère. | G8: À vérifier. | H8: Gastronomie thaïe d'excellence, quasi absente de Paris (philosophie du projet). | I8: Via l'organisateur de Dalad's | J8: A | K8: Base et disponibilités | L8: S15 | M8: À qualifier | O8: Vérifier la situation actuelle
A9: CH08 | B9: Aboubakar Bamba | C9: 4. Second ou ancien d'une maison étoilée | D9: Gastronomique | E9: Candidat Top Chef 2026 ; chef privé à Paris ; passé chez David Toutain (2 étoiles). | F9: Chef privé. | G9: Élevée. | H9: Formé dans une grande maison, sans restaurant, notoriété télévisée. | I9: Compte professionnel | J9: A | L9: S16 | M9: À qualifier | O9: Vérifier la situation actuelle
A10: CH09 | B10: Flavio Lucarini et Aurora Storari | C10: 1. Chef étoilé en transition | D10: Gastronomie italienne / pâtisserie | E10: Chef et cheffe pâtissière d'Hémicycle (étoilé, Paris 7e), fermé fin 2025 ; passés à Substance (même groupe). | F10: En poste à Substance (Paris 16e). | G10: Moyenne : Substance est fermé samedi et dimanche (base HEC Cuisine Innovation). | H10: Duo chef + pâtissière, cuisine italienne d'auteur. | I10: Via Substance | J10: B | K10: Rôle exact à Substance | L10: S6 | M10: À qualifier | O10: Vérifier la situation actuelle
A11: CH10 | B11: Viviana Pisacane | C11: 2. Chef étoilé hors Paris, déjà venu en pop-up | D11: Italienne (Naples) / lyonnaise | E11: Gagnante de Top Chef 2026 (finale du 10/06/2026, brigade d'Hélène Darroze) ; dirige Le Bœuf d'Argent (Vieux Lyon). | F11: En poste à Lyon. | G11: Notoriété télévisée très récente ; déplacements à prévoir. | H11: Visage connu du grand public, absente de Paris. | I11: Via Le Bœuf d'Argent / agent | J11: B | K11: Agent et sollicitations | L11: S10 | M11: À qualifier | O11: Vérifier la situation actuelle
A12: CH11 | B12: Raimundo Briones | C12: 3. Chef indépendant / pop-up / supper club | D12: Chilienne / créative | E12: Chef chilien, ancien architecte ; supper club ACR Paris en lieu non dévoilé et commandes privées (guide promotionnel, 01/06/2026). | F12: Sans adresse fixe. | G12: Élevée. | H12: Déjà rodé aux dîners privés en lieu secret. | I12: Compte professionnel ACR Paris | J12: B | K12: Soirées déclarées (licence, hygiène) | L12: S14 | M12: À qualifier | O12: Vérifier la situation actuelle
A13: CH12 | B13: Matteo Pioppi | C13: 4. Second ou ancien d'une maison étoilée | D13: Gastronomique | E13: Candidat Top Chef 2026 ; sous-chef de Blanc (Paris). | F13: En poste (sous-chef). | G13: Soirées ponctuelles avec accord de l'employeur. | H13: Profil « second d'un grand restaurant » visé par le cadre. | I13: Compte professionnel | J13: B | K13: Accord de l'employeur | L13: S16 | M13: À qualifier | O13: Vérifier la situation actuelle
A14: CH13 | B14: Dylan Bury | C14: 4. Second ou ancien d'une maison étoilée | D14: Gastronomique classique | E14: Candidat Top Chef 2026 ; sous-chef de Maison Rostang (2 étoiles historiques). | F14: En poste (sous-chef). | G14: Soirées ponctuelles avec accord de l'employeur. | H14: Second d'une grande maison parisienne. | I14: Compte professionnel | J14: B | K14: Accord de l'employeur | L14: S16 | M14: À qualifier | O14: Vérifier la situation actuelle
A15: CH14 | B15: Benjamin Le Moal | C15: 5. Chef privé passé par l'étoilé | D15: Gastronomie sur mesure | E15: Formé à Ferrandi ; expérience en maisons étoilées ; chef privé haut de gamme depuis 2013 (selon son site). | F15: Chef privé. | G15: Élevée. | H15: Habitué d'une clientèle exigeante et internationale, à domicile. | I15: Site professionnel | J15: B | K15: Maisons étoilées précises | L15: S18 | M15: À qualifier | O15: Vérifier la situation actuelle
A16: CH15 | B16: Jihyun Kim | C16: 6. Nouveau talent distingué en 2026 (en poste) | D16: Coréenne / gastronomique | E16: « Jeune talent » Gault&Millau Île-de-France 2026 ; cheffe d'Ébène (Paris 15e). | F16: En poste. | G16: Faible à moyenne. | H16: Cuisine coréenne d'auteur, rare à Paris. | I16: Via Ébène | J16: B | L16: S20 | M16: À qualifier | O16: Vérifier la situation actuelle
A17: CH16 | B17: Khelil Morin | C17: 6. Nouveau talent distingué en 2026 (en poste) | D17: À préciser | E17: Lauréat de la dotation Jeunes Talents Gault&Millau 2026 pour son projet Mara (Paris). | F17: Restaurant en projet. | G17: Élevée avant ouverture. | H17: Soirées test avant l'ouverture de son restaurant : intérêt mutuel. | I17: Via Gault&Millau / compte professionnel | J17: B | K17: Date d'ouverture de Mara | L17: S21 | M17: À qualifier | O17: Vérifier la situation actuelle
A18: CH17 | B18: Philip Chronopoulos | C18: 1. Chef étoilé en transition | D18: Gastronomie française | E18: Chef du Palais Royal Restaurant (Paris 1er), fermé définitivement ; reprend les cuisines du Taillevent (2 étoiles). | F18: En poste au Taillevent. | G18: Faible : chef d'une maison 2 étoiles. | H18: Grand nom pour une soirée exceptionnelle ou à quatre mains. | I18: Via Le Taillevent | J18: C | K18: Date de prise de poste | L18: S4, S5 | M18: À qualifier | O18: Vérifier la situation actuelle
A19: CH18 | B19: Romain Meder | C19: 4. Second ou ancien d'une maison étoilée | D19: Gastronomie naturelle | E19: Chef de Prévelle (Paris 7e), étoilé en 2026 ; ancien chef d'Alain Ducasse au Plaza Athénée. | F19: En poste. | G19: Faible à moyenne. | H19: Parcours de palace 3 étoiles ; soirée exceptionnelle ou à quatre mains. | I19: Via Prévelle | J19: C | L19: S17, S16 | M19: À qualifier | O19: Vérifier la situation actuelle
A20: CH19 | B20: Loïc Krimm | C20: 5. Chef privé passé par l'étoilé | D20: Gastronomie française | E20: Passé par des maisons 1 et 2 étoiles ; demi-finaliste de la Coupe du monde des chefs à domicile (Paris, septembre 2025) (selon son site). | F20: Chef privé. | G20: Élevée. | H20: Chef privé à parcours étoilé. | I20: Site professionnel | J20: C | K20: Maisons étoilées précises | L20: S19 | M20: À qualifier | O20: Vérifier la situation actuelle
A21: CH20 | B21: Takuya Watanabe | C21: 6. Nouveau talent distingué en 2026 (en poste) | D21: Japonaise | E21: Chef de Hakuba (Paris 1er), passé à 2 étoiles en 2026. | F21: En poste. | G21: Faible. | H21: Grande cuisine japonaise, rare à Paris ; soirée exceptionnelle. | I21: Via Hakuba | J21: C | L21: S17 | M21: À qualifier | O21: Vérifier la situation actuelle
A22: CH21 | B22: Shawn Joyeux et Toshitaka Omiya | C22: 6. Nouveau talent distingué en 2026 (en poste) | D22: Franco-japonaise | E22: Chefs d'Alliance (Paris 5e), passé à 2 étoiles en 2026. | F22: En poste. | G22: Faible. | H22: Duo reconnu ; soirée à quatre mains. | I22: Via Alliance | J22: C | L22: S17 | M22: À qualifier | O22: Vérifier la situation actuelle
A23: CH22 | B23: Camille Gouyer et Frédéric Lorimier | C23: 6. Nouveau talent distingué en 2026 (en poste) | D23: Gastronomique | E23: Chefs de Virtus (Paris 12e), passé à 2 étoiles en 2026. | F23: En poste. | G23: Faible. | H23: Duo reconnu ; soirée à quatre mains. | I23: Via Virtus | J23: C | L23: S17 | M23: À qualifier | O23: Vérifier la situation actuelle
A24: CH23 | B24: Martino Ruggieri | C24: 6. Nouveau talent distingué en 2026 (en poste) | D24: Italienne gastronomique | E24: Maison Ruggieri (Palais Royal), 1 étoile en 2026 après déménagement. | F24: En poste. | G24: Faible. | H24: Grande cuisine italienne : soirée « Italie » du cadre. | I24: Via Maison Ruggieri | J24: C | L24: S17, S6 | M24: À qualifier | O24: Vérifier la situation actuelle
A25: CH24 | B25: Arthur Dubois | C25: 6. Nouveau talent distingué en 2026 (en poste) | D25: Gastronomique | E25: Chef d'Héritages (Paris 8e), étoilé en 2026. | F25: En poste. | G25: Faible à moyenne. | H25: Jeune étoilé. | I25: Via Héritages | J25: C | L25: S17 | M25: À qualifier | O25: Vérifier la situation actuelle
A26: CH25 | B26: Julien Dumas | C26: 6. Nouveau talent distingué en 2026 (en poste) | D26: Gastronomique | E26: Chef de Zostera (Paris 16e), étoilé en 2026. | F26: En poste. | G26: Faible à moyenne. | H26: Jeune étoilé. | I26: Via Zostera | J26: C | L26: S17 | M26: À qualifier | O26: Vérifier la situation actuelle
A27: CH26 | B27: Jason Gouzy | C27: 6. Nouveau talent distingué en 2026 (en poste) | D27: Gastronomique | E27: « Grand de demain » Gault&Millau Île-de-France 2026, pour Pantagruel (Paris 1er). | F27: En poste. | G27: Faible à moyenne. | H27: Distinction récente. | I27: Via Pantagruel | J27: C | L27: S20 | M27: À qualifier | O27: Vérifier la situation actuelle
A28: CH27 | B28: Tom Meyer | C28: 7. Meilleur Ouvrier de France | D28: Gastronomique | E28: Meilleur Ouvrier de France (novembre 2022) ; chef de Granite (Paris 1er), fermé samedi et dimanche (base HEC Cuisine Innovation). | F28: En poste. | G28: Faible à moyenne. | H28: Titre MOF : argument de prestige. | I28: Via Granite | J28: C | L28: S22 | M28: À qualifier | O28: Vérifier la situation actuelle
A29: CH28 | B29: Christophe Raoux | C29: 7. Meilleur Ouvrier de France | D29: Française classique | E29: Meilleur Ouvrier de France 2015 ; chef exécutif du Café de la Paix et des restaurants de l'InterContinental Paris Le Grand (à la date de la source). | F29: Probablement en poste (source ancienne). | G29: À vérifier. | H29: Titre MOF, expérience des grands volumes. | I29: Via l'hôtel | J29: C | K29: Poste actuel | L29: S23 | M29: À qualifier | O29: Vérifier la situation actuelle

Sheet Sources
A1: Réf. | B1: Source | C1: Lien | D1: Date
A2: S1 | B2: Au cœur du CHR, Boris Campanella quitte l'Hôtel de Crillon | C2: https://aucoeurduchr.fr/article/nominations-et-mouvements/boris-campanella-quitte-crillon/ | D2: fin 2025
A3: S2 | B3: Gault&Millau, L'Écrin va bientôt fermer | C3: https://fr.gaultmillau.com/en/news/l-ecrin-restaurant-4-toques-de-l-hotel-de-crillon-va-bientot-fermer | D3: 2025
A4: S3 | B4: Sortiraparis, fermeture de Yam'Tcha | C4: https://www.sortiraparis.com/actualites/a-paris/articles/338500-fermeture-de-yam-tcha-le-restaurant-etoile-d-adeline-grattard-a-paris | D4: décembre 2025
A5: S4 | B5: L'Hôtellerie Restauration, Michelin 2026 : rétrogradations et suppressions | C5: https://www.lhotellerie-restauration.fr/actualite/michelin-2026-les-retrogradations-et-suppressions | D5: mars 2026
A6: S5 | B6: Gilles Pudlowski, Michelin 2026 : les suppressions d'étoiles | C6: https://www.gillespudlowski.com/421381/actualites/michelin-2026-les-suppressions-detoiles | D6: mars 2026
A7: S6 | B7: Paris by Mouth, Hémicycle (now closed) | C7: https://parisbymouth.com/hemicycle/ | D7: fin 2025
A8: S7 | B8: Guide Michelin, pop-up de Florent Pietravalle au Lutetia | C8: https://guide.michelin.com/en/article/travel/paris-pop-up-lutetia-hotel-florent-pietravalle | D8: 09/07/2025
A9: S8 | B9: Time Out Paris, la cuisine étoilée de Florent Pietravalle s'installe à Paris | C9: https://www.timeout.fr/paris/actualites/rouget-langoustine-caviar-la-cuisine-etoilee-de-florent-pietravalle-sinstalle-a-paris-061125 | D9: juin 2025
A10: S9 | B10: Gault&Millau, Alexandre Gauthier ouvre un restaurant éphémère à Paris | C10: https://fr.gaultmillau.com/fr/news/alexandre-gauthier-ouvre-un-restaurant-ephemere-a-paris | D10: avril 2024
A11: S10 | B11: Sortiraparis, Top Chef 2026 : qui a gagné la saison 17 | C11: https://www.sortiraparis.com/en/what-to-do-in-paris/cinema-series/articles/347097-top-chef-2026-who-will-win-the-17th-season | D11: juin 2026
A12: S11 | B12: Sortiraparis, Cramat' d'Alexy | C12: https://www.sortiraparis.com/en/where-to-eat-in-paris/restaurant/articles/347128-alexy-top-chef-finalist-opens-a-pop-up-restaurant-named-cramat-on-the-outskirts-of-paris | D12: 2026
... A24: S23 | B24: Hospitality On, Christophe Raoux MOF 2015 | C24: https://hospitality-on.com/fr/restauration/christophe-raoux-cafe-de-la-paix-lun-des-mof-2015 | D24: 2015
