Workbook

Sheet Synthèse
A1: Prospects entreprises par catégorie : Paris et Île-de-France
A2: Légende : VERT = donnée réelle publiée (source citée) | ORANGE = estimation ou hypothèse (calcul de Claude)
A3: Plateforme de location de restaurants les jours de fermeture (surtout dimanche et lundi soir) à des flying chefs. Cible entreprises : dîners et afterworks du lundi soir.
A5: Catégorie | B5: Sous-catégorie | C5: Prospects Paris | D5: Prospects IdF | E5: Unité | F5: Priorité | G5: Événements / prospect / an | H5: Budget moyen par événement (€) | I5: Marché potentiel Paris (€ / an) | J5: Fiabilité
A6: 1. Startups et scale-ups | B6: Startups et scale-ups de 50 à 300 salariés | C6: ='1 Startups scale-ups'!$C$21 -> 248.00985 | D6: =IF(ISNUMBER('1 Startups scale-ups'!$D$21),'1 Startups scale-ups'!$D$21,"n.d.") -> 435.105 | E6: entreprises | F6: Haute | G6: 2 | H6: 2500 | I6: =C6*G6*H6 -> 1240049.3 | J6: Faible
A7: 1. Startups et scale-ups | B7: Startups de 20 à 49 salariés | C7: ='1 Startups scale-ups'!$C$22 -> 440.9064 | D7: =IF(ISNUMBER('1 Startups scale-ups'!$D$22),'1 Startups scale-ups'!$D$22,"n.d.") -> 773.52 | E7: entreprises | F7: Moyenne | G7: 1 | H7: 2000 | I7: =C7*G7*H7 -> 881812.8 | J7: Faible
A8: 2. Agences et conseil | B8: Agences de com / pub de 10 salariés ou plus | C8: ='2 Agences conseil'!$C$11 -> 651.75 | D8: =IF(ISNUMBER('2 Agences conseil'!$D$11),'2 Agences conseil'!$D$11,"n.d.") -> 1185 | E8: agences | F8: Haute | G8: 2 | H8: 2500 | I8: =C8*G8*H8 -> 3258750 | J8: Moyenne
A9: 2. Agences et conseil | B9: Agences de design de 10 salariés ou plus | C9: ='2 Agences conseil'!$C$12 -> 150 | D9: =IF(ISNUMBER('2 Agences conseil'!$D$12),'2 Agences conseil'!$D$12,"n.d.") -> 220 | E9: agences | F9: Moyenne | G9: 1 | H9: 2000 | I9: =C9*G9*H9 -> 300000 | J9: Faible
A10: 2. Agences et conseil | B10: Cabinets d'avocats de plus de 10 avocats | C10: ='2 Agences conseil'!$C$20 -> 205.03297 | D10: =IF(ISNUMBER('2 Agences conseil'!$D$20),'2 Agences conseil'!$D$20,"n.d.") -> n.d. | E10: cabinets | F10: Haute | G10: 3 | H10: 3500 | I10: =C10*G10*H10 -> 2152846.2 | J10: Moyenne
A11: 2. Agences et conseil | B11: Équipes Big Four (40 pers.) | C11: ='2 Agences conseil'!$C$25 -> 469.625 | D11: =IF(ISNUMBER('2 Agences conseil'!$D$25),'2 Agences conseil'!$D$25,"n.d.") -> n.d. | E11: équipes | F11: Moyenne | G11: 1 | H11: 3000 | I11: =C11*G11*H11 -> 1408875 | J11: Moyenne
A12: 2. Agences et conseil | B12: Conseil en stratégie / management de 20+ salariés | C12: ='2 Agences conseil'!$C$26 -> 300 | D12: =IF(ISNUMBER('2 Agences conseil'!$D$26),'2 Agences conseil'!$D$26,"n.d.") -> 400 | E12: cabinets | F12: Haute | G12: 2 | H12: 3500 | I12: =C12*G12*H12 -> 2100000 | J12: Faible
A13: 3. CSE grandes entreprises | B13: CSE de 1 000 salariés ou plus | C13: ='3 CSE'!$C$16 -> 270 | D13: =IF(ISNUMBER('3 CSE'!$D$16),'3 CSE'!$D$16,"n.d.") -> 725 | E13: CSE | F13: Haute | G13: 4 | H13: 2000 | I13: =C13*G13*H13 -> 2160000 | J13: Moyenne
A14: 3. CSE grandes entreprises | B14: CSE de 300 à 999 salariés | C14: ='3 CSE'!$C$15 -> 720 | D14: =IF(ISNUMBER('3 CSE'!$D$15),'3 CSE'!$D$15,"n.d.") -> 1885 | E14: CSE | F14: Haute | G14: 2 | H14: 2000 | I14: =C14*G14*H14 -> 2880000 | J14: Moyenne
A15: 3. CSE grandes entreprises | B15: CSE de 50 à 299 salariés | C15: ='3 CSE'!$C$17 -> 3510 | D15: =IF(ISNUMBER('3 CSE'!$D$17),'3 CSE'!$D$17,"n.d.") -> 11890 | E15: CSE | F15: Basse | G15: 0.5 | H15: 1500 | I15: =C15*G15*H15 -> 2632500 | J15: Moyenne
A16: 4. RH et marque employeur | B16: Équipes RH / office managers (établissements 50+) | C16: ='4 RH marque employeur'!$C$13 -> 3868.9 | D16: =IF(ISNUMBER('4 RH marque employeur'!$D$13),'4 RH marque employeur'!$D$13,"n.d.") -> 11221.2 | E16: équipes RH | F16: Haute | G16: 1 | H16: 2500 | I16: =C16*G16*H16 -> 9672250 | J16: Moyenne
A17: TOTAL (avec recoupements) | C17: =SUM(C6:C16) -> 10834.224 | D17: =SUM(D6:D16) -> 28734.825 | I17: =SUM(I6:I16) -> 28687083
A19: Volumes complémentaires (pour dimensionner la demande)
B20: Salariés des établissements de 50+ à Paris | C20: ='3 CSE'!$C$8 -> 1110000
B21: Enveloppe ASC totale des CSE à Paris (€ / an) | C21: ='3 CSE'!$C$23 -> 532800000
B22: dont « loisirs et sorties » adressable (€ / an) | C22: ='3 CSE'!$C$25 -> 133200000
B23: Pots de départ hors les murs par an à Paris | C23: ='4 RH marque employeur'!$C$20 -> 8325
B24: Séminaires / dîners d'équipe de 15-40 pers. par an à Paris | C24: ='4 RH marque employeur'!$C$22 -> 44400
B25: Lundis soir disponibles par an | C25: 52
A27: Comment lire ce tableau
A28: • Les chiffres de prospects sont des ordres de grandeur. Seules les données de cadrage (onglets 1 à 4, cellules vertes) sont publiées ; les comptages par sous-catégorie sont des estimations (orange).
A29: • Les catégories se recoupent : une scale-up de 150 salariés a aussi un CSE et une équipe RH. Le total surestime donc le nombre d'entreprises distinctes, d'environ 30 à 40 %.
A30: • Colonnes G et H (texte bleu) = hypothèses modifiables : nombre d'événements par prospect et par an, budget moyen d'un événement (location de salle + chef + repas). Le marché potentiel se recalcule.
A31: • Le marché potentiel suppose que 100 % des prospects achètent : c'est un plafond, pas une prévision. Une part de marché réaliste en année 1 serait de l'ordre de 1 à 3 %.
A32: • Prochaine étape pour fiabiliser : extraction SIRENE (annuaire-entreprises.data.gouv.fr) par code NAF, tranche d'effectif et code postal, pour remplacer les cellules orange par des comptages réels.

Sheet 1 Startups scale-ups
A1: Cible 1 : Startups et scale-ups de 50 à 300 salariés
A2: Légende : VERT = donnée réelle publiée (source citée) | ORANGE = estimation ou hypothèse (calcul de Claude)
A3: Culture « team dinner », budgets CSE sous-utilisés, goût pour les lieux atypiques. Zones : Station F (13e), 2e, 9e, 10e, 11e.
A5: Indicateur | B5: Unité | C5: Paris (75) | D5: Île-de-France | E5: Type | F5: Source / méthode
A6: Données de cadrage
A7: Startups actives en France | B7: entreprises | C7: n.d. | D7: 18000 | E7: Réel | F7: Panorama French Tech 2025 (Mission French Tech / Motherbase), oct. 2025. Blog du Modérateur 17/10/2025 : https://www.blogdumoderateur.com/panorama-french-tech-2025/ (valeur France entière, placée en colonne IdF faute de mieux : voir ligne suivante)
A8: Start-up en Île-de-France (définition Insee) | B8: entreprises | C8: n.d. | D8: 8790 | E8: Réel | F8: Insee Analyses Île-de-France n° 209, sept. 2025, données 2022 : « Plus d'une start-up française sur trois est localisée en Île-de-France » https://www.insee.fr/fr/statistiques/8647906
A9: Part de Paris dans l'emploi salarié des start-up franciliennes | B9: % | C9: 0.57 | D9: n.d. | E9: Réel | F9: CCI Paris IdF (Crocis), Enjeux IdF n° 267, nov. 2025 : Paris = 57 % de l'emploi salarié des start-up. https://www.cci-paris-idf.fr/fr/prospective/crocis/economie/start-up-emploi
A10: Emploi salarié des start-up franciliennes (ETP) | B10: ETP | C10: =D10*'1 Startups scale-ups'!$C$9 -> 46569 | D10: 81700 | E10: Réel | F10: CCI Paris IdF (Crocis) / Insee, données 2022 : 81 700 ETP, taille moyenne 9,3 ETP. Les 10 % de start-up les plus grandes concentrent 60 % de l'emploi.
A11: Part des start-up franciliennes qui sont des TPE (moins de 10 salariés) | B11: % | C11: n.d. | D11: 0.69 | E11: Réel | F11: Insee Analyses IdF n° 209 : « ce n'est le cas que de 69 % des start-up ».
A12: Emploi moyen des 10 % de start-up les plus grandes | B12: ETP / entreprise | C12: n.d. | D12: =D10*0.6/(D8*0.1) -> 55.767918 | E12: Estimation | F12: Calcul : 60 % de 81 700 ETP répartis sur 10 % de 8 790 start-up, soit environ 56 ETP en moyenne. Montre que le seuil de 50 salariés concerne moins de 10 % des start-up.
A13: Projets accompagnés chaque année par Station F (13e) | B13: startups / an | C13: 1000 | D13: n.d. | E13: Réel | F13: Maddyness, 24/06/2026 : Station F accompagne « un millier de projets » par an ; plus de 9 000 startups passées par le campus. Ce sont surtout des jeunes pousses de moins de 50 salariés : vivier d'équipes de 10 à 40 personnes.
A15: Hypothèses de répartition par taille
A16: Part des start-up de 50 à 300 salariés | B16: % | C16: n.d. | D16: 0.045 | E16: Estimation | F16: Hypothèse : 31 % des start-up ont 10 salariés ou plus (Insee) et les 10 % plus grandes ont 56 ETP en moyenne : on retient environ 4,5 % entre 50 et 300 salariés. À valider avec la base SIRENE (tranches 50-99, 100-199, 200-249, 250-499) croisée avec la liste French Tech.
A17: Part des start-up de 20 à 49 salariés (cible secondaire) | B17: % | C17: n.d. | D17: 0.08 | E17: Estimation | F17: Hypothèse, même méthode. Ces équipes ont souvent la taille idéale (15-40 personnes) pour une salle de restaurant mais pas de CSE.
A18: Croissance du nombre de start-up 2022 → 2026 | B18: % | C18: n.d. | D18: 0.1 | E18: Estimation | F18: Hypothèse prudente. La CCI mesure +27 % entre 2017 et 2022 ; l'emploi French Tech progresse encore (+4,6 % au 1er semestre 2025).
A20: Prospects
A21: Startups et scale-ups de 50 à 300 salariés (CIBLE PRINCIPALE) | B21: entreprises | C21: =D21*'1 Startups scale-ups'!$C$9 -> 248.00985 | D21: ='1 Startups scale-ups'!$D$8*'1 Startups scale-ups'!$D$16*(1+'1 Startups scale-ups'!$D$18) -> 435.105 | E21: Estimation | F21: IdF = 8 790 x 4,5 % x 1,10. Paris = IdF x 57 %.
A22: Startups de 20 à 49 salariés (cible secondaire) | B22: entreprises | C22: =D22*'1 Startups scale-ups'!$C$9 -> 440.9064 | D22: ='1 Startups scale-ups'!$D$8*'1 Startups scale-ups'!$D$17*(1+'1 Startups scale-ups'!$D$18) -> 773.52 | E22: Estimation | F22: IdF = 8 790 x 8 % x 1,10. Paris = IdF x 57 %.
A23: Salariés dans la cible principale (moyenne de 110 salariés) | B23: salariés | C23: =C21*110 -> 27281.084 | D23: =D21*110 -> 47861.55 | E23: Estimation | F23: Hypothèse : 110 salariés en moyenne entre 50 et 300 (distribution très concentrée vers le bas).
A25: Zones citées (Station F, 2e, 9e, 10e, 11e) : pas de comptage officiel par arrondissement. Pour les cibler, filtrer la base SIRENE (codes NAF 58.29, 62.01, 62.02, 63.12, tranche d'effectif 50+) par code postal 75002, 75009, 75010, 75011, 75013. Liste de départ utile : French Tech 120 / Next40 (120 entreprises).

Sheet 2 Agences conseil
A1: Cible 2 : Agences et cabinets de conseil
A2: Légende : VERT = donnée réelle publiée (source citée) | ORANGE = estimation ou hypothèse (calcul de Claude)
A3: Com, pub, design, avocats d'affaires, Big Four : dîners clients et soirées de fin de projet, un chef invité comme argument d'image.
A5: Indicateur | B5: Unité | C5: Paris (75) | D5: Île-de-France | E5: Type | F5: Source / méthode
A6: 2a. Agences de communication et de publicité
A7: Agences de publicité et de conseil en communication | B7: établissements | C7: n.d. | D7: 23700 | E7: Réel | F7: CCI Paris IdF (Crocis), Enjeux IdF n° 211 « La révolution numérique bouleverse les agences conseils en communication et publicité d'Île-de-France » : plus de 23 700 agences, 45 % des agences françaises. https://www.cci-paris-idf.fr/fr/prospective/crocis/services/revolution-numerique-bouleverse-agences-conseils-communication-publicite-75 (données de la fin des années 2010)
A8: Salariés des agences | B8: salariés | C8: n.d. | D8: 45800 | E8: Réel | F8: Même source : 45 800 salariés en IdF (47 % de la France), dont plus de 70 % à Paris et dans les Hauts-de-Seine.
A9: Part de Paris dans les agences franciliennes | B9: % | C9: 0.55 | D9: n.d. | E9: Estimation | F9: Hypothèse : plus de 70 % pour Paris + Hauts-de-Seine réunis (source ci-dessus), dont environ 55 % pour Paris seul.
A10: Part des agences de 10 salariés ou plus | B10: % | C10: n.d. | D10: 0.05 | E10: Estimation | F10: Hypothèse : 45 800 salariés pour 23 700 agences, soit moins de 2 salariés en moyenne. L'immense majorité sont des indépendants ou des micro-agences.
A11: Agences de com / pub de 10 salariés ou plus (prospects) | B11: agences | C11: =D11*'2 Agences conseil'!$C$9 -> 651.75 | D11: ='2 Agences conseil'!$D$7*'2 Agences conseil'!$D$10 -> 1185 | E11: Estimation | F11: IdF = 23 700 x 5 %. Paris = IdF x 55 %.
A12: Agences de design, d'architecture intérieure et studios de création de 10 salariés ou plus | B12: agences | C12: 150 | D12: 220 | E12: Estimation | F12: Ordre de grandeur à valider via SIRENE (NAF 74.10Z Activités spécialisées de design, tranche 10+).
A14: 2b. Cabinets d'avocats
A15: Avocats inscrits au barreau de Paris | B15: avocats | C15: 30526 | D15: n.d. | E15: Réel | F15: Ordre des avocats de Paris, chiffres clés au 10/03/2020 : https://www.avocatparis.org/actualites/chiffres-cles-des-avocats-du-barreau-de-paris (environ 40 % des avocats de France)
A16: Structures d'exercice : SELARL + SELARLU + AARPI (types principaux) | B16: structures | C16: 2886 | D16: n.d. | E16: Réel | F16: Même source : 1 342 SELARLU, 843 SELARL, 701 AARPI. Ne compte pas les SCP, SAS, bureaux de cabinets étrangers, etc.
A17: Part des avocats exerçant dans un cabinet de 11 à 20 avocats | B17: % | C17: 0.07 | D17: n.d. | E17: Réel | F17: Enquête emploi des avocats 2026, Viavoice pour le CNB (6 083 répondants, Paris = 44 %), fév. 2026.
A18: Part des avocats exerçant dans un cabinet de 21 à 30 avocats | B18: % | C18: 0.02 | D18: n.d. | E18: Réel | F18: Même source.
A19: Part des avocats exerçant dans un cabinet de plus de 30 avocats | B19: % | C19: 0.1 | D19: n.d. | E19: Réel | F19: Même source. Échantillon national : à Paris la part des grands cabinets est sans doute plus élevée.
A20: Cabinets d'avocats de plus de 10 avocats à Paris (prospects) | B20: cabinets | C20: ='2 Agences conseil'!$C$15*'2 Agences conseil'!$C$17/15+'2 Agences conseil'!$C$15*'2 Agences conseil'!$C$18/25+'2 Agences conseil'!$C$15*'2 Agences conseil'!$C$19/80 -> 205.03297 | D20: n.d. | E20: Estimation | F20: Estimation : avocats de chaque tranche ÷ taille moyenne supposée (15, 25, 80 avocats). Les cabinets d'affaires anglo-saxons et les grands cabinets français sont concentrés dans les 8e, 16e et 17e.
A22: 2c. Big Four et conseil en stratégie / management
A23: Effectif France des Big Four (Deloitte, EY, KPMG, PwC) | B23: collaborateurs | C23: n.d. | D23: 28900 | E23: Réel | F23: Rapports de transparence 2025 cités par consulting-numerique.com/big-four : Deloitte 8 800 (France + Afrique francophone), EY plus de 6 500, KPMG plus de 6 600, PwC 7 000 (France + Maghreb). Total légèrement surestimé pour la France seule.
A24: Part de l'effectif Big Four basée à Paris / La Défense | B24: % | C24: 0.65 | D24: n.d. | E24: Estimation | F24: Hypothèse : sièges à Paris-La Défense (Neuilly, Courbevoie), réseau de bureaux régionaux.
A25: Équipes Big Four acheteuses (une équipe ou practice de 40 personnes) | B25: équipes | C25: ='2 Agences conseil'!$D$23*'2 Agences conseil'!$C$24/40 -> 469.625 | D25: n.d. | E25: Estimation | F25: Estimation : le vrai décideur est l'associé ou le manager d'une équipe, pas le cabinet. 4 groupes, mais environ 470 budgets d'équipe.
A26: Cabinets de conseil en stratégie / management de 20 salariés ou plus | B26: cabinets | C26: 300 | D26: 400 | E26: Estimation | F26: Ordre de grandeur à valider via SIRENE (NAF 70.22Z, tranche 20+). Le marché français du conseil en stratégie et management pèse environ 8,8 Md€ (Consultor, 2021), concentré en IdF.
A28: Total cible 2
A29: Total prospects Agences et conseil | B29: prospects | C29: =C11+C12+C20+C25+C26 -> 1776.408 | D29: n.d. | E29: Estimation | F29: Somme des lignes « prospects » ci-dessus (Paris).

Sheet 3 CSE
A1: Cible 3 : CSE des grandes entreprises
A2: Légende : VERT = donnée réelle publiée (source citée) | ORANGE = estimation ou hypothèse (calcul de Claude)
A3: Activités originales pour les salariés (atelier ou dîner avec un chef), vendues en billetterie. Le CSE est obligatoire à partir de 50 salariés.
A5: Indicateur | B5: Unité | C5: Paris (75) | D5: Île-de-France | E5: Type | F5: Source / méthode
A6: Données de cadrage
A7: Établissements de 50 salariés ou plus | B7: établissements | C7: 5527 | D7: 18702 | E7: Réel | F7: Insee, Flores fin 2022 (données déjà validées dans le projet).
A8: Salariés de ces établissements | B8: salariés | C8: 1110000 | D8: 3850000 | E8: Réel | F8: Insee, Flores fin 2022.
A9: Part des entreprises de 50 à 299 salariés dotées d'une instance élue | B9: % | C9: 0.84 | D9: 0.84 | E9: Réel | F9: DARES, enquête REPONSE / Analyses 2021.
A10: CSE avec budget ASC (entreprises et établissements) | B10: CSE | C10: 4500 | D10: 14500 | E10: Estimation | F10: Estimation déjà retenue dans le projet : 13 000 à 16 000 en IdF, 4 000 à 5 000 à Paris (milieu de fourchette). Moins que le nombre d'établissements car plusieurs établissements partagent un CSE central, et 84 % seulement en ont un.
A12: Segmentation par taille (cible « grandes entreprises » = 300 salariés ou plus)
A13: Part des CSE couvrant 300 salariés ou plus | B13: % | C13: 0.22 | D13: 0.18 | E13: Estimation | F13: Hypothèse : dans la structure Insee des établissements de 50+, environ 80 % ont 50 à 299 salariés. Paris compte plus de sièges sociaux, d'où une part plus élevée.
A14: Part des CSE couvrant 1 000 salariés ou plus | B14: % | C14: 0.06 | D14: 0.05 | E14: Estimation | F14: Hypothèse, même logique.
A15: CSE de 300 à 999 salariés (CIBLE PRINCIPALE) | B15: CSE | C15: ='3 CSE'!$C$10*('3 CSE'!$C$13-'3 CSE'!$C$14) -> 720 | D15: ='3 CSE'!$D$10*('3 CSE'!$D$13-'3 CSE'!$D$14) -> 1885 | E15: Estimation | F15: Ont un budget ASC significatif, souvent un élu dédié aux activités et une billetterie en ligne.
A16: CSE de 1 000 salariés ou plus (grands comptes) | B16: CSE | C16: ='3 CSE'!$C$10*'3 CSE'!$C$14 -> 270 | D16: ='3 CSE'!$D$10*'3 CSE'!$D$14 -> 725 | E16: Estimation | F16: Souvent équipés de plateformes de billetterie (Meyclub, Kalidea, Pluxee…) : un référencement dans ces catalogues peut toucher beaucoup de CSE d'un coup.
A17: CSE de 50 à 299 salariés (cible secondaire) | B17: CSE | C17: ='3 CSE'!$C$10*(1-'3 CSE'!$C$13) -> 3510 | D17: ='3 CSE'!$D$10*(1-'3 CSE'!$D$13) -> 11890 | E17: Estimation | F17: Budgets plus faibles, souvent sous-utilisés : recoupe en partie la cible 1 (startups).
A19: Budget des activités sociales et culturelles (ASC)
A20: Budget ASC moyen en % de la masse salariale brute | B20: % | C20: 0.008 | D20: 0.008 | E20: Réel | F20: Estimation du Sénat (2013) : environ 0,8 % de la masse salariale brute, citée par LegalPlace https://www.legalplace.fr/guides/budget-asc-cse/ . Pas de minimum légal ; certains accords fixent 0,5 % à 1,25 %.
A21: Salaire brut annuel moyen (salariés des établissements de 50+) | B21: € / an | C21: 60000 | D21: 52000 | E21: Estimation | F21: Hypothèse d'ordre de grandeur pour Paris et l'IdF (à affiner avec Insee, base Tous salariés).
A22: Budget ASC par salarié et par an | B22: € / salarié | C22: ='3 CSE'!$C$21*'3 CSE'!$C$20 -> 480 | D22: ='3 CSE'!$D$21*'3 CSE'!$D$20 -> 416 | E22: Estimation | F22: Salaire brut moyen x 0,8 %.
A23: Enveloppe ASC totale (établissements de 50+) | B23: € / an | C23: ='3 CSE'!$C$8*'3 CSE'!$C$22 -> 532800000 | D23: ='3 CSE'!$D$8*'3 CSE'!$D$22 -> 1601600000 | E23: Estimation | F23: Salariés x budget ASC par salarié. Ordre de grandeur de la « poche » dans laquelle la plateforme doit prendre une part.
A24: Part de l'enveloppe ASC consacrée aux sorties, loisirs et culture | B24: % | C24: 0.25 | D24: 0.25 | E24: Estimation | F24: Hypothèse : le reste va surtout aux chèques-cadeaux, vacances et billetterie de spectacles.
A25: Enveloppe « loisirs et sorties » adressable | B25: € / an | C25: ='3 CSE'!$C$23*'3 CSE'!$C$24 -> 133200000 | D25: ='3 CSE'!$D$23*'3 CSE'!$D$24 -> 400400000 | E25: Estimation | F25: Enveloppe ASC x 25 %.

Sheet 4 RH marque employeur
A1: Cible 4 : Équipes RH et marque employeur
A2: Légende : VERT = donnée réelle publiée (source citée) | ORANGE = estimation ou hypothèse (calcul de Claude)
A3: Onboarding, pots de départ, séminaires de petites équipes de 15 à 40 personnes. Le prospect est la direction RH (ou l'office manager) de chaque entreprise.
A5: Indicateur | B5: Unité | C5: Paris (75) | D5: Île-de-France | E5: Type | F5: Source / méthode
A6: Données de cadrage
A7: Établissements de 50 salariés ou plus | B7: établissements | C7: 5527 | D7: 18702 | E7: Réel | F7: Insee, Flores fin 2022.
A8: Salariés de ces établissements | B8: salariés | C8: 1110000 | D8: 3850000 | E8: Réel | F8: Insee, Flores fin 2022.
A9: Emploi salarié total | B9: salariés | C9: n.d. | D9: 6341800 | E9: Réel | F9: Insee Conjoncture Île-de-France, bilan 2024 (juin 2025) : 6 341 800 salariés fin 2024. Les DPAE (embauches) reculent de 4,5 % à Paris en 2024.
A11: Prospects
A12: Part des établissements de 50+ ayant une fonction RH ou office manager sur place | B12: % | C12: 0.7 | D12: 0.6 | E12: Estimation | F12: Hypothèse : les établissements secondaires (agences, magasins) dépendent souvent d'une DRH située ailleurs ; Paris concentre les sièges.
A13: Équipes RH / office managers prospects (établissements de 50+) | B13: équipes RH | C13: ='4 RH marque employeur'!$C$7*'4 RH marque employeur'!$C$12 -> 3868.9 | D13: ='4 RH marque employeur'!$D$7*'4 RH marque employeur'!$D$12 -> 11221.2 | E13: Estimation | F13: Établissements de 50+ x part avec RH sur place.
A14: Managers d'équipes de 15 à 40 personnes (décideurs pour un séminaire d'équipe) | B14: équipes | C14: ='4 RH marque employeur'!$C$8/25 -> 44400 | D14: ='4 RH marque employeur'!$D$8/25 -> 154000 | E14: Estimation | F14: Hypothèse : une équipe de 25 personnes en moyenne. C'est le vrai nombre de « budgets d'équipe » qui peuvent réserver.
A16: Occasions par an (volume d'événements théorique)
A17: Taux de départ annuel des salariés (turnover) | B17: % | C17: 0.15 | D17: 0.15 | E17: Estimation | F17: Hypothèse : 15 % par an dans les entreprises tertiaires de 50+ (CDD exclus).
A18: Départs par an dans les établissements de 50+ | B18: départs | C18: ='4 RH marque employeur'!$C$8*'4 RH marque employeur'!$C$17 -> 166500 | D18: ='4 RH marque employeur'!$D$8*'4 RH marque employeur'!$D$17 -> 577500 | E18: Estimation | F18: Salariés x turnover : autant d'arrivées (onboarding) que de départs (pots de départ).
A19: Part des départs donnant lieu à un pot hors du bureau | B19: % | C19: 0.05 | D19: 0.05 | E19: Estimation | F19: Hypothèse : la plupart des pots restent au bureau ou au bar d'à côté.
A20: Pots de départ hors les murs par an | B20: événements / an | C20: ='4 RH marque employeur'!$C$18*'4 RH marque employeur'!$C$19 -> 8325 | D20: ='4 RH marque employeur'!$D$18*'4 RH marque employeur'!$D$19 -> 28875 | E20: Estimation | F20: Départs x 5 %.
A21: Séminaires ou dîners d'équipe hors les murs par équipe et par an | B21: par équipe | C21: 1 | D21: 1 | E21: Estimation | F21: Hypothèse : un événement d'équipe par an (séminaire, fin d'année, team building).
A22: Séminaires et dîners d'équipe de 15 à 40 personnes par an | B22: événements / an | C22: ='4 RH marque employeur'!$C$14*'4 RH marque employeur'!$C$21 -> 44400 | D22: ='4 RH marque employeur'!$D$14*'4 RH marque employeur'!$D$21 -> 154000 | E22: Estimation | F22: Équipes x 1 événement par an.

Sheet Sources & méthode
A1: Sources et méthode
A2: Légende : VERT = donnée réelle publiée (source citée) | ORANGE = estimation ou hypothèse (calcul de Claude)
A3: Toutes les sources consultées le 28/10/2026.
A5: Source | B5: Ce qu'on en tire | C5: Lien
A6: Insee Analyses Île-de-France n° 209 (sept. 2025, données 2022) | B6: 8 790 start-up en IdF, 69 % de TPE, Paris > 50 % des start-up | C6: https://www.insee.fr/fr/statistiques/8647906
A7: CCI Paris IdF, Crocis, Enjeux IdF n° 267 (nov. 2025) | B7: 81 700 ETP dans les start-up franciliennes, 57 % de l'emploi à Paris, top 10 % = 60 % de l'emploi | C7: https://www.cci-paris-idf.fr/fr/prospective/crocis/economie/start-up-emploi
A8: Panorama French Tech 2025 (Blog du Modérateur, 17/10/2025) | B8: 18 000 startups, 450 000 emplois en France | C8: https://www.blogdumoderateur.com/panorama-french-tech-2025/
A9: Maddyness, 24/06/2026 | B9: Station F : un millier de projets accompagnés par an, 9 000+ startups passées par le campus | C9: https://www.maddyness.com/2026/06/24/comment-se-porte-station-f-a-laube-de-feter-sa-premiere-decennie-dexistence/
A10: CCI Paris IdF, Crocis, Enjeux IdF n° 211 | B10: 23 700 agences de pub / com en IdF, 45 800 salariés, 70 % à Paris + 92 | C10: https://www.cci-paris-idf.fr/fr/prospective/crocis/services/revolution-numerique-bouleverse-agences-conseils-communication-publicite-75
A11: Ordre des avocats de Paris, chiffres clés (mars 2020) | B11: 30 526 avocats ; 1 342 SELARLU, 843 SELARL, 701 AARPI | C11: https://www.avocatparis.org/actualites/chiffres-cles-des-avocats-du-barreau-de-paris
A12: CNB / Viavoice, Enquête emploi des avocats 2026 | B12: Répartition des avocats par taille de cabinet | C12: https://cnb.avocat.fr/medias/file/enquete-emploi-avocats-2026---viavoice-pour-le-cnb-6a10296eec05a6.15527835.pdf
A13: Rapports de transparence Big Four 2025 (via consulting-numerique.com) | B13: Effectifs France : Deloitte 8 800, EY 6 500, KPMG 6 600, PwC 7 000 | C13: https://consulting-numerique.com/big-four
A14: Insee, Flores fin 2022 (déjà dans le projet) | B14: 18 702 établissements de 50+ en IdF (3,85 M salariés), 5 527 à Paris (1,11 M) | C14: insee.fr
A15: DARES 2021 | B15: 84 % des entreprises de 50 à 299 salariés ont une instance élue | C15: dares.travail-emploi.gouv.fr
A16: LegalPlace, citant le Sénat (2013) | B16: Budget ASC moyen environ 0,8 % de la masse salariale brute | C16: https://www.legalplace.fr/guides/budget-asc-cse/
A17: Insee Conjoncture IdF, bilan 2024 (juin 2025) | B17: 6,34 M salariés en IdF fin 2024 ; DPAE -4,5 % à Paris | C17: https://www.insee.fr/fr/statistiques/fichier/8354209/if_inc_54_emploi.pdf
A19: Limites :
A20: • Pas d'accès direct à la base SIRENE depuis l'environnement de travail : les comptages par code NAF x tranche d'effectif x arrondissement restent à faire.
A21: • Les chiffres des agences de communication (Crocis n° 211) et des avocats (2020) datent de plusieurs années ; les volumes ont probablement augmenté.
A22: • Le budget ASC moyen (0,8 %) est une estimation ancienne du Sénat, il n'existe pas de statistique officielle récente.
