Workbook

Sheet Lisez-moi
A1: Pop Tables — Population cible des groupes constitués
A2: Pôle Ventes · 28/10/2026 · Consolidation de « 4 VENTES/CLIENTS/2026 1028 Demarchage des groupes - Offres evenementielles.md » · Document de travail
A4: Code couleur
A5: Ligne blanche : organisation de la liste Ventes du 28/10 (30 organisations).
A6: Ligne BLEUE : proposition ajoutée par l'assistant IA, à valider (8 pistes).
A7: Cellule VERTE : nombre de membres publié par une source (citée à droite). Chiffre de presse ou du club lui-même : ordre de grandeur, pas un comptage.
A8: Cellule ORANGE : hypothèse ou estimation, modifiable ; tous les totaux se recalculent.
A9: Cellule GRISE : effectif non établi par les sources ; à demander lors de la qualification. Ces organisations ne comptent pas dans les totaux.
A11: Comment lire les chiffres
A12: « Membres retenus » = effectif parisien ou français utilisé pour le calcul (valeur basse quand les sources divergent). Les effectifs mondiaux (Chaîne des Rôtisseurs, YPO…) ne sont pas comptés : seul l'effectif parisien compte, et il n'est pas publié.
A13: Les cercles se recoupent : une même personne peut être membre de l'ACF, du Jockey Club et du Siècle. Le total est un plafond, pas un nombre de personnes distinctes.
A14: Le potentiel (onglet Population cible, colonnes orange) applique les hypothèses de l'onglet « Hypothèses » : part des membres qui viendraient à une soirée dans l'année, jauge et prix de la privatisation du cadre Pop Tables (D-05, D-10).
... A17: Aucun contact ni partenariat n'est acquis. Un membre intéressé n'est pas un accord de son club. Ne pas démarcher des membres à partir d'annuaires privés. Pas de nom de décideur dans le dépôt (RULES.md) : seulement le rôle.

Sheet Synthèse
A1: Population cible des groupes constitués : synthèse
A2: Calcul en direct depuis l'onglet « Population cible ». Les membres retenus additionnent des cercles qui se recoupent : c'est un plafond. Organisations sans effectif publié : non comptées.
A4: Famille | B4: Organisations (liste) | C4: Propositions ajoutées | D4: Avec effectif chiffré | E4: Membres retenus | F4: Convives potentiels / an (H) | G4: Privatisations équivalentes / an (H) | H4: CA potentiel € TTC / an (H)
A5: 1. Clubs gastronomiques | B5: =COUNTIFS('Population cible'!$B$2:$B$39,A5,'Population cible'!$A$2:$A$39,"Liste Ventes du 28/10") | C5: =COUNTIFS('Population cible'!$B$2:$B$39,A5,'Population cible'!$A$2:$A$39,"Proposition ajoutée") | D5: =COUNTIFS('Population cible'!$B$2:$B$39,A5,'Population cible'!$H$2:$H$39,">0") | E5: =SUMIFS('Population cible'!$H$2:$H$39,'Population cible'!$B$2:$B$39,A5) | F5: =SUMIFS('Population cible'!$I$2:$I$39,'Population cible'!$B$2:$B$39,A5) | G5: =SUMIFS('Population cible'!$J$2:$J$39,'Population cible'!$B$2:$B$39,A5) | H5: =SUMIFS('Population cible'!$K$2:$K$39,'Population cible'!$B$2:$B$39,A5)
A6: 2. Clubs de vin | B6: =COUNTIFS('Population cible'!$B$2:$B$39,A6,'Population cible'!$A$2:$A$39,"Liste Ventes du 28/10") | C6: =COUNTIFS('Population cible'!$B$2:$B$39,A6,'Population cible'!$A$2:$A$39,"Proposition ajoutée") | D6: =COUNTIFS('Population cible'!$B$2:$B$39,A6,'Population cible'!$H$2:$H$39,">0") | E6: =SUMIFS('Population cible'!$H$2:$H$39,'Population cible'!$B$2:$B$39,A6) | F6: =SUMIFS('Population cible'!$I$2:$I$39,'Population cible'!$B$2:$B$39,A6) | G6: =SUMIFS('Population cible'!$J$2:$J$39,'Population cible'!$B$2:$B$39,A6) | H6: =SUMIFS('Population cible'!$K$2:$K$39,'Population cible'!$B$2:$B$39,A6)
A7: 3. Cercles privés et clubs d'affaires | B7: =COUNTIFS('Population cible'!$B$2:$B$39,A7,'Population cible'!$A$2:$A$39,"Liste Ventes du 28/10") | C7: =COUNTIFS('Population cible'!$B$2:$B$39,A7,'Population cible'!$A$2:$A$39,"Proposition ajoutée") | D7: =COUNTIFS('Population cible'!$B$2:$B$39,A7,'Population cible'!$H$2:$H$39,">0") | E7: =SUMIFS('Population cible'!$H$2:$H$39,'Population cible'!$B$2:$B$39,A7) | F7: =SUMIFS('Population cible'!$I$2:$I$39,'Population cible'!$B$2:$B$39,A7) | G7: =SUMIFS('Population cible'!$J$2:$J$39,'Population cible'!$B$2:$B$39,A7) | H7: =SUMIFS('Population cible'!$K$2:$K$39,'Population cible'!$B$2:$B$39,A7)
A8: 4. Réseaux alumni | B8: =COUNTIFS('Population cible'!$B$2:$B$39,A8,'Population cible'!$A$2:$A$39,"Liste Ventes du 28/10") | C8: =COUNTIFS('Population cible'!$B$2:$B$39,A8,'Population cible'!$A$2:$A$39,"Proposition ajoutée") | D8: =COUNTIFS('Population cible'!$B$2:$B$39,A8,'Population cible'!$H$2:$H$39,">0") | E8: =SUMIFS('Population cible'!$H$2:$H$39,'Population cible'!$B$2:$B$39,A8) | F8: =SUMIFS('Population cible'!$I$2:$I$39,'Population cible'!$B$2:$B$39,A8) | G8: =SUMIFS('Population cible'!$J$2:$J$39,'Population cible'!$B$2:$B$39,A8) | H8: =SUMIFS('Population cible'!$K$2:$K$39,'Population cible'!$B$2:$B$39,A8)
A9: 5. Réseaux de dirigeants | B9: =COUNTIFS('Population cible'!$B$2:$B$39,A9,'Population cible'!$A$2:$A$39,"Liste Ventes du 28/10") | C9: =COUNTIFS('Population cible'!$B$2:$B$39,A9,'Population cible'!$A$2:$A$39,"Proposition ajoutée") | D9: =COUNTIFS('Population cible'!$B$2:$B$39,A9,'Population cible'!$H$2:$H$39,">0") | E9: =SUMIFS('Population cible'!$H$2:$H$39,'Population cible'!$B$2:$B$39,A9) | F9: =SUMIFS('Population cible'!$I$2:$I$39,'Population cible'!$B$2:$B$39,A9) | G9: =SUMIFS('Population cible'!$J$2:$J$39,'Population cible'!$B$2:$B$39,A9) | H9: =SUMIFS('Population cible'!$K$2:$K$39,'Population cible'!$B$2:$B$39,A9)
A10: Total | B10: =SUM(B5:B9) | C10: =SUM(C5:C9) | D10: =SUM(D5:D9) | E10: =SUM(E5:E9) | F10: =SUM(F5:F9) | G10: =SUM(G5:G9) | H10: =SUM(H5:H9)
A12: Liste seule vs avec propositions
A13: Périmètre | B13: Organisations | C13: Avec effectif chiffré | D13: Membres retenus | E13: Convives potentiels / an (H)
A14: Liste Ventes du 28/10 seule | B14: =COUNTIF('Population cible'!$A$2:$A$39,"Liste Ventes du 28/10") | C14: =COUNTIFS('Population cible'!$A$2:$A$39,"Liste Ventes du 28/10",'Population cible'!$H$2:$H$39,">0") | D14: =SUMIFS('Population cible'!$H$2:$H$39,'Population cible'!$A$2:$A$39,"Liste Ventes du 28/10") | E14: =SUMIFS('Population cible'!$I$2:$I$39,'Population cible'!$A$2:$A$39,"Liste Ventes du 28/10")
A15: Propositions ajoutées seules | B15: =COUNTIF('Population cible'!$A$2:$A$39,"Proposition ajoutée") | C15: =COUNTIFS('Population cible'!$A$2:$A$39,"Proposition ajoutée",'Population cible'!$H$2:$H$39,">0") | D15: =SUMIFS('Population cible'!$H$2:$H$39,'Population cible'!$A$2:$A$39,"Proposition ajoutée") | E15: =SUMIFS('Population cible'!$I$2:$I$39,'Population cible'!$A$2:$A$39,"Proposition ajoutée")
A18: Lecture
A19: • Les cercles privés portent l'essentiel de la population chiffrée (ACF, Union Interalliée, Jockey Club, Saint James, Le Siècle).
A20: • Clubs de vin : aucun effectif publié ; ce sont pourtant les plus proches du concept (chef, lieu, cave). Premier chiffre à obtenir en rendez-vous.
A21: • Pépites et Cookoon sont des concurrents-partenaires : leurs membres sont une population cible, leur club n'est pas un client.
A22: • Les clubs APM (proposition) sont déjà des groupes constitués de 20 dirigeants environ : la jauge exacte d'une privatisation Pop Tables.

Sheet Population cible
A1: Origine | B1: Famille | C1: Organisation | D1: Priorité | E1: Rôle | F1: Membres (chiffre publié) | G1: Périmètre du chiffre | H1: Membres retenus pour le calcul | I1: Convives potentiels / an | J1: Privatisations équivalentes / an | K1: CA potentiel € TTC / an | L1: Source du chiffre | M1: Angle proposé | N1: Statut | O1: Prochaine action | P1: Responsable
A2: Liste Ventes du 28/10 | B2: 1. Clubs gastronomiques | C2: Club des Cent | D2: P1 relationnel | E2: Acheteur (groupe de membres) | F2: 100 membres officiels | G2: Paris | H2: 100 | I2: =IF(H2="","",ROUND(H2*Hypothèses!$B$3,0)) | J2: =IF(H2="","",ROUND(I2/Hypothèses!$B$4,1)) | K2: =IF(H2="","",J2*Hypothèses!$B$7) | L2: Wikipédia, Club des Cent | M2: Dîner réellement différent de leur programmation ; via un membre introducteur | N2: À qualifier | O2: Vérifier l'activité et l'effectif
A3: Liste Ventes du 28/10 | B3: 1. Clubs gastronomiques | C3: Chaîne des Rôtisseurs — France et bailliages | D3: P1 | E3: Acheteur (bailliage) | F3: ≈ 25 000 membres dans le monde | G3: Monde | I3: =IF(H3="","",ROUND(H3*Hypothèses!$B$3,0)) | J3: =IF(H3="","",ROUND(I3/Hypothèses!$B$4,1)) | K3: =IF(H3="","",J3*Hypothèses!$B$7) | L3: Site France de la Chaîne des Rôtisseurs | M3: Soirée pour un groupe constitué ; demander l'effectif du bailliage de Paris | N3: À qualifier | O3: Vérifier l'activité et l'effectif
A4: Liste Ventes du 28/10 | B4: 1. Clubs gastronomiques | C4: Club Prosper Montagné | D4: P1 | E4: Acheteur | F4: Non établi | I4: =IF(H4="","",ROUND(H4*Hypothèses!$B$3,0)) | J4: =IF(H4="","",ROUND(I4/Hypothèses!$B$4,1)) | K4: =IF(H4="","",J4*Hypothèses!$B$7) | M4: Rencontre gastronomique pour membres | N4: À qualifier | O4: Vérifier l'activité et l'effectif
A5: Liste Ventes du 28/10 | B5: 1. Clubs gastronomiques | C5: Club Pépites | D5: P2 concurrent-partenaire | E5: Concurrent-partenaire | F5: Plafonné à 1 000 membres ; plus des trois quarts des places prises | G5: Paris | H5: 750 | I5: =IF(H5="","",ROUND(H5*Hypothèses!$B$3,0)) | J5: =IF(H5="","",ROUND(I5/Hypothèses!$B$4,1)) | K5: =IF(H5="","",J5*Hypothèses!$B$7) | L5: Site Pépites (« le club des 1000 ») ; Paris Zigzag | M5: Complémentarité à étudier ; pas un simple prospect | N5: À qualifier | O5: Vérifier l'activité et l'effectif
A6: Liste Ventes du 28/10 | B6: 1. Clubs gastronomiques | C6: Académie Internationale des Gourmets et des Traditions Gastronomiques — AIGTG | D6: P2 | E6: Acheteur | F6: Non établi | I6: =IF(H6="","",ROUND(H6*Hypothèses!$B$3,0)) | J6: =IF(H6="","",ROUND(I6/Hypothèses!$B$4,1)) | K6: =IF(H6="","",J6*Hypothèses!$B$7) | M6: Manifestation réservée aux membres | N6: À qualifier | O6: Vérifier l'activité et l'effectif
A7: Liste Ventes du 28/10 | B7: 1. Clubs gastronomiques | C7: Disciples Escoffier | D7: P2 | E7: Prescripteur (chefs) et convives | F7: 10 000 à 36 000 membres dans le monde selon les sources | G7: Monde | I7: =IF(H7="","",ROUND(H7*Hypothèses!$B$3,0)) | J7: =IF(H7="","",ROUND(I7/Hypothèses!$B$4,1)) | K7: =IF(H7="","",J7*Hypothèses!$B$7) | L7: Echo du Mardi 2025 ; L'Express Madagascar 2025 | M7: Réseau mixte chefs / convives ; chiffre France non publié | N7: À qualifier | O7: Vérifier l'activité et l'effectif
A8: Liste Ventes du 28/10 | B8: 1. Clubs gastronomiques | C8: Cookoon | D8: P2 concurrent-partenaire | E8: Concurrent-partenaire | F8: ≈ 2 500 adhérents (chiffre du club) | G8: Paris | H8: 2500 | I8: =IF(H8="","",ROUND(H8*Hypothèses!$B$3,0)) | J8: =IF(H8="","",ROUND(I8/Hypothèses!$B$4,1)) | K8: =IF(H8="","",J8*Hypothèses!$B$7) | L8: Infrarouge, 7 clubs à Paris (2024) | M8: Benchmark et coproduction éventuelle ; activité à reconfirmer | N8: À qualifier | O8: Vérifier l'activité et l'effectif
A9: Liste Ventes du 28/10 | B9: 1. Clubs gastronomiques | C9: Prémices | D9: P2 concurrent-partenaire | E9: Concurrent-partenaire | F9: Non établi | I9: =IF(H9="","",ROUND(H9*Hypothèses!$B$3,0)) | J9: =IF(H9="","",ROUND(I9/Hypothèses!$B$4,1)) | K9: =IF(H9="","",J9*Hypothèses!$B$7) | M9: Qualifier une complémentarité | N9: À qualifier | O9: Vérifier l'activité et l'effectif
A10: Liste Ventes du 28/10 | B10: 1. Clubs gastronomiques | C10: Académie des gastronomes | D10: P3 à vérifier | E10: Acheteur | F10: Non établi | I10: =IF(H10="","",ROUND(H10*Hypothèses!$B$3,0)) | J10: =IF(H10="","",ROUND(I10/Hypothèses!$B$4,1)) | K10: =IF(H10="","",J10*Hypothèses!$B$7) | M10: Activité actuelle à vérifier | N10: À qualifier | O10: Vérifier l'activité et l'effectif
A11: Liste Ventes du 28/10 | B11: 2. Clubs de vin | C11: Cercle WB / Wine & Business Club | D11: P1 | E11: Acheteur | F11: Non établi | I11: =IF(H11="","",ROUND(H11*Hypothèses!$B$3,0)) | J11: =IF(H11="","",ROUND(I11/Hypothèses!$B$4,1)) | K11: =IF(H11="","",J11*Hypothèses!$B$7) | M11: Dîner membres ou clients | N11: À qualifier | O11: Vérifier l'activité et l'effectif
A12: Liste Ventes du 28/10 | B12: 2. Clubs de vin | C12: Chais d'œuvre | D12: P1 | E12: Acheteur | F12: Non établi | I12: =IF(H12="","",ROUND(H12*Hypothèses!$B$3,0)) | J12: =IF(H12="","",ROUND(I12/Hypothèses!$B$4,1)) | K12: =IF(H12="","",J12*Hypothèses!$B$7) | M12: Accords mets-vins et chef invité | N12: À qualifier | O12: Vérifier l'activité et l'effectif
A13: Liste Ventes du 28/10 | B13: 2. Clubs de vin | C13: Cep Club de France | D13: P1 | E13: Acheteur | F13: Non établi | I13: =IF(H13="","",ROUND(H13*Hypothèses!$B$3,0)) | J13: =IF(H13="","",ROUND(I13/Hypothèses!$B$4,1)) | K13: =IF(H13="","",J13*Hypothèses!$B$7) | M13: Dîner de grands vins pour membres | N13: À qualifier | O13: Vérifier l'activité et l'effectif
A14: Liste Ventes du 28/10 | B14: 2. Clubs de vin | C14: Club Rouge aux Lèvres | D14: P2 | E14: Acheteur | F14: Non établi | I14: =IF(H14="","",ROUND(H14*Hypothèses!$B$3,0)) | J14: =IF(H14="","",ROUND(I14/Hypothèses!$B$4,1)) | K14: =IF(H14="","",J14*Hypothèses!$B$7) | M14: Dîner thématique ; budget à qualifier | N14: À qualifier | O14: Vérifier l'activité et l'effectif
A15: Liste Ventes du 28/10 | B15: 2. Clubs de vin | C15: Cercle des Œnophiles de Paris | D15: P2 | E15: Acheteur | F15: Non établi | I15: =IF(H15="","",ROUND(H15*Hypothèses!$B$3,0)) | J15: =IF(H15="","",ROUND(I15/Hypothèses!$B$4,1)) | K15: =IF(H15="","",J15*Hypothèses!$B$7) | M15: Soirée mets-vins ; budget à qualifier | N15: À qualifier | O15: Vérifier l'activité et l'effectif
A16: Liste Ventes du 28/10 | B16: 2. Clubs de vin | C16: Club Epicure inVINSctus Paris by Terra Hominis | D16: P3 à vérifier | E16: Acheteur | F16: Non établi | I16: =IF(H16="","",ROUND(H16*Hypothèses!$B$3,0)) | J16: =IF(H16="","",ROUND(I16/Hypothèses!$B$4,1)) | K16: =IF(H16="","",J16*Hypothèses!$B$7) | M16: Club en création : activité à confirmer | N16: À qualifier | O16: Vérifier l'activité et l'effectif
A17: Liste Ventes du 28/10 | B17: 2. Clubs de vin | C17: Vin Heures 17 | D17: P3 | E17: Acheteur | F17: Non établi | I17: =IF(H17="","",ROUND(H17*Hypothèses!$B$3,0)) | J17: =IF(H17="","",ROUND(I17/Hypothèses!$B$4,1)) | K17: =IF(H17="","",J17*Hypothèses!$B$7) | M17: Dîner pour un sous-groupe ; budget premium à tester | N17: À qualifier | O17: Vérifier l'activité et l'effectif
A18: Liste Ventes du 28/10 | B18: 3. Cercles privés et clubs d'affaires | C18: Automobile Club de France — ACF | D18: P1 relationnel | E18: Acheteur (cercle) | F18: ≈ 2 200 membres (hommes uniquement) | G18: Paris | H18: 2200 | I18: =IF(H18="","",ROUND(H18*Hypothèses!$B$3,0)) | J18: =IF(H18="","",ROUND(I18/Hypothèses!$B$4,1)) | K18: =IF(H18="","",J18*Hypothèses!$B$7) | L18: Wikipédia FR ; PassionAndCar 2016 | M18: Expérience complémentaire hors les murs | N18: À qualifier | O18: Vérifier l'activité et l'effectif
A19: Liste Ventes du 28/10 | B19: 3. Cercles privés et clubs d'affaires | C19: Cercle de l'Union Interalliée | D19: P1 relationnel | E19: Acheteur (cercle) | F19: 3 100 à 3 300 membres selon les versions | G19: Paris | H19: 3100 | I19: =IF(H19="","",ROUND(H19*Hypothèses!$B$3,0)) | J19: =IF(H19="","",ROUND(I19/Hypothèses!$B$4,1)) | K19: =IF(H19="","",J19*Hypothèses!$B$7) | L19: Wikipédia (EN et FR) | M19: Soirée de membres | N19: À qualifier | O19: Vérifier l'activité et l'effectif
A20: Liste Ventes du 28/10 | B20: 3. Cercles privés et clubs d'affaires | C20: Travellers Club Paris | D20: P1 relationnel | E20: Acheteur (cercle) | F20: Non établi | I20: =IF(H20="","",ROUND(H20*Hypothèses!$B$3,0)) | J20: =IF(H20="","",ROUND(I20/Hypothèses!$B$4,1)) | K20: =IF(H20="","",J20*Hypothèses!$B$7) | M20: Chef international ; via introduction | N20: À qualifier | O20: Vérifier l'activité et l'effectif
A21: Liste Ventes du 28/10 | B21: 3. Cercles privés et clubs d'affaires | C21: Saint James Club Paris | D21: P1 | E21: Acheteur (cercle) | F21: 650 à 800 membres selon les sources | G21: Paris | H21: 650 | I21: =IF(H21="","",ROUND(H21*Hypothèses!$B$3,0)) | J21: =IF(H21="","",ROUND(I21/Hypothèses!$B$4,1)) | K21: =IF(H21="","",J21*Hypothèses!$B$7) | L21: Wikipédia FR (650) ; WCB 2023 (750) ; Infrarouge (800) | M21: Programmation complémentaire | N21: À qualifier | O21: Vérifier l'activité et l'effectif
A22: Liste Ventes du 28/10 | B22: 3. Cercles privés et clubs d'affaires | C22: Jockey Club de Paris | D22: P2 relationnel | E22: Acheteur (cercle) | F22: ≈ 1 200 membres | G22: Paris | H22: 1200 | I22: =IF(H22="","",ROUND(H22*Hypothèses!$B$3,0)) | J22: =IF(H22="","",ROUND(I22/Hypothèses!$B$4,1)) | K22: =IF(H22="","",J22*Hypothèses!$B$7) | L22: La Libre Belgique, 16/08/2023 | M22: Groupe constitué via un membre | N22: À qualifier | O22: Vérifier l'activité et l'effectif
A23: Liste Ventes du 28/10 | B23: 3. Cercles privés et clubs d'affaires | C23: Soho House Paris | D23: P2 | E23: Acheteur / programmateur | F23: Non établi | I23: =IF(H23="","",ROUND(H23*Hypothèses!$B$3,0)) | J23: =IF(H23="","",ROUND(I23/Hypothèses!$B$4,1)) | K23: =IF(H23="","",J23*Hypothèses!$B$7) | L23: Plateya 2026 (tarifs seulement) | M23: Chef invité ; collaboration extérieure à qualifier | N23: À qualifier | O23: Vérifier l'activité et l'effectif
A24: Liste Ventes du 28/10 | B24: 3. Cercles privés et clubs d'affaires | C24: Silencio | D24: P2 | E24: Programmateur | F24: Non établi | I24: =IF(H24="","",ROUND(H24*Hypothèses!$B$3,0)) | J24: =IF(H24="","",ROUND(I24/Hypothèses!$B$4,1)) | K24: =IF(H24="","",J24*Hypothèses!$B$7) | M24: Gastronomie et culture ; format à vérifier | N24: À qualifier | O24: Vérifier l'activité et l'effectif
A25: Liste Ventes du 28/10 | B25: 3. Cercles privés et clubs d'affaires | C25: We Are | D25: P2 | E25: Acheteur | F25: Non établi | I25: =IF(H25="","",ROUND(H25*Hypothèses!$B$3,0)) | J25: =IF(H25="","",ROUND(I25/Hypothèses!$B$4,1)) | K25: =IF(H25="","",J25*Hypothèses!$B$7) | L25: Plateya 2026 (tarifs seulement) | M25: Soirée de communauté ou d'affaires | N25: À qualifier | O25: Vérifier l'activité et l'effectif
A26: Liste Ventes du 28/10 | B26: 3. Cercles privés et clubs d'affaires | C26: The Circle — Maison Villeroy | D26: P2 | E26: Acheteur | F26: Non établi | I26: =IF(H26="","",ROUND(H26*Hypothèses!$B$3,0)) | J26: =IF(H26="","",ROUND(I26/Hypothèses!$B$4,1)) | K26: =IF(H26="","",J26*Hypothèses!$B$7) | M26: Expérience personnalisée ; offre à confirmer | N26: À qualifier | O26: Vérifier l'activité et l'effectif
A27: Liste Ventes du 28/10 | B27: 3. Cercles privés et clubs d'affaires | C27: Polo de Paris | D27: P2 relationnel | E27: Acheteur | F27: Non établi | I27: =IF(H27="","",ROUND(H27*Hypothèses!$B$3,0)) | J27: =IF(H27="","",ROUND(I27/Hypothèses!$B$4,1)) | K27: =IF(H27="","",J27*Hypothèses!$B$7) | M27: Art de vivre ; programme à qualifier | N27: À qualifier | O27: Vérifier l'activité et l'effectif
A28: Liste Ventes du 28/10 | B28: 3. Cercles privés et clubs d'affaires | C28: Le Siècle | D28: P3 relationnel | E28: Hôtes d'affaires (individuels) | F28: 751 membres + 159 invités ; 766 en 2020 | G28: Paris | H28: 751 | I28: =IF(H28="","",ROUND(H28*Hypothèses!$B$3,0)) | J28: =IF(H28="","",ROUND(I28/Hypothèses!$B$4,1)) | K28: =IF(H28="","",J28*Hypothèses!$B$7) | L28: Reporterre ; Breizh-Info 03/03/2021 (presse, chiffres non officiels) | M28: Réseau relationnel, pas un club gastronomique | N28: À qualifier | O28: Vérifier l'activité et l'effectif
A29: Liste Ventes du 28/10 | B29: 3. Cercles privés et clubs d'affaires | C29: Cercle de l'Union | D29: P3 relationnel | E29: Acheteur (cercle) | F29: Non établi | I29: =IF(H29="","",ROUND(H29*Hypothèses!$B$3,0)) | J29: =IF(H29="","",ROUND(I29/Hypothèses!$B$4,1)) | K29: =IF(H29="","",J29*Hypothèses!$B$7) | M29: Dîner privé via introduction | N29: À qualifier | O29: Vérifier l'activité et l'effectif
A30: Liste Ventes du 28/10 | B30: 4. Réseaux alumni | C30: Club HEC VINS — HEC Alumni | D30: P1 | E30: Acheteur (club) | F30: Club non chiffré ; HEC Alumni ≈ 80 000 membres de la communauté | G30: Monde | I30: =IF(H30="","",ROUND(H30*Hypothèses!$B$3,0)) | J30: =IF(H30="","",ROUND(I30/Hypothèses!$B$4,1)) | K30: =IF(H30="","",J30*Hypothèses!$B$7) | L30: L'Express Éducation (communauté HEC) | M30: Chef invité et grands vins ; effectif du club à demander | N30: À qualifier | O30: Vérifier l'activité et l'effectif
A31: Liste Ventes du 28/10 | B31: 4. Réseaux alumni | C31: ESSEC Alumni Wine, Whisky & Spirits | D31: P1 | E31: Acheteur (club) | F31: Club non chiffré ; ESSEC ≈ 74 000 diplômés | G31: Monde | I31: =IF(H31="","",ROUND(H31*Hypothèses!$B$3,0)) | J31: =IF(H31="","",ROUND(I31/Hypothèses!$B$4,1)) | K31: =IF(H31="","",J31*Hypothèses!$B$7) | L31: Misterprepa (diplômés par école) | M31: Soirée prestige, éventuellement interclubs | N31: À qualifier | O31: Vérifier l'activité et l'effectif
A32: Proposition ajoutée | B32: 5. Réseaux de dirigeants | C32: APM — Association Progrès du Management (clubs de Paris) | D32: P1 (proposé) | E32: Acheteur (club de dirigeants) | F32: ≈ 9 000 adhérents en 440 clubs ; 35 clubs à Paris | G32: Paris (35 clubs) | H32: 700 | I32: =IF(H32="","",ROUND(H32*Hypothèses!$B$3,0)) | J32: =IF(H32="","",ROUND(I32/Hypothèses!$B$4,1)) | K32: =IF(H32="","",J32*Hypothèses!$B$7) | L32: Le Journal des Entreprises 2026 ; apm.fr | M32: Un club APM = un groupe constitué de 20 dirigeants : format privatisation (20 couverts). Estimation : 35 clubs × 20 membres | N32: À qualifier | O32: Vérifier l'activité et l'effectif
A33: Proposition ajoutée | B33: 5. Réseaux de dirigeants | C33: YPO — chapitre de Paris | D33: P1 (proposé) | E33: Acheteur (forums de dirigeants) | F33: 34 000 à 38 000 membres dans le monde | G33: Monde | I33: =IF(H33="","",ROUND(H33*Hypothèses!$B$3,0)) | J33: =IF(H33="","",ROUND(I33/Hypothèses!$B$4,1)) | K33: =IF(H33="","",J33*Hypothèses!$B$7) | L33: ypo.org | M33: Dîners de forum ou de couples ; effectif parisien à demander | N33: À qualifier | O33: Vérifier l'activité et l'effectif
A34: Proposition ajoutée | B34: 5. Réseaux de dirigeants | C34: EO Paris — Entrepreneurs' Organization | D34: P2 (proposé) | E34: Acheteur (forums d'entrepreneurs) | F34: 20 000 membres dans le monde, 220 chapitres | G34: Monde | I34: =IF(H34="","",ROUND(H34*Hypothèses!$B$3,0)) | J34: =IF(H34="","",ROUND(I34/Hypothèses!$B$4,1)) | K34: =IF(H34="","",J34*Hypothèses!$B$7) | L34: eo-paris.fr | M34: Soirée de chapitre ou de forum | N34: À qualifier | O34: Vérifier l'activité et l'effectif
A35: Proposition ajoutée | B35: 4. Réseaux alumni | C35: Harvard Club of France (et HBS Club of France) | D35: P2 (proposé) | E35: Acheteur (club) | F35: 1 500+ membres (Harvard Club) ; 1 500+ (HBS Club) | G35: France | H35: 1500 | I35: =IF(H35="","",ROUND(H35*Hypothèses!$B$3,0)) | J35: =IF(H35="","",ROUND(I35/Hypothèses!$B$4,1)) | K35: =IF(H35="","",J35*Hypothèses!$B$7) | L35: harvardclub.fr | M35: Dîner de prestige pour alumni ; recoupement possible entre les deux clubs | N35: À qualifier | O35: Vérifier l'activité et l'effectif
A36: Proposition ajoutée | B36: 4. Réseaux alumni | C36: Autres alumni premium : Polytechnique (AX), Sciences Po Alumni, INSEAD | D36: P2 (proposé) | E36: Acheteur (clubs vins / gastronomie) | F36: Non établi | I36: =IF(H36="","",ROUND(H36*Hypothèses!$B$3,0)) | J36: =IF(H36="","",ROUND(I36/Hypothèses!$B$4,1)) | K36: =IF(H36="","",J36*Hypothèses!$B$7) | M36: Chercher leurs clubs œnologie ou art de vivre, sur le modèle de HEC VINS | N36: À qualifier | O36: Vérifier l'activité et l'effectif
A37: Proposition ajoutée | B37: 1. Clubs gastronomiques | C37: Club des Croqueurs de Chocolat | D37: P3 (proposé) | E37: Acheteur | F37: Non établi | I37: =IF(H37="","",ROUND(H37*Hypothèses!$B$3,0)) | J37: =IF(H37="","",ROUND(I37/Hypothèses!$B$4,1)) | K37: =IF(H37="","",J37*Hypothèses!$B$7) | L37: Wikipédia, Club des Croqueurs de Chocolat | M37: Soirée chef pâtissier ou cacao | N37: À qualifier | O37: Vérifier l'activité et l'effectif
A38: Proposition ajoutée | B38: 3. Cercles privés et clubs d'affaires | C38: Yacht Club de France | D38: P3 (proposé) | E38: Acheteur (cercle) | F38: Non établi | I38: =IF(H38="","",ROUND(H38*Hypothèses!$B$3,0)) | J38: =IF(H38="","",ROUND(I38/Hypothèses!$B$4,1)) | K38: =IF(H38="","",J38*Hypothèses!$B$7) | L38: Bateaux.com (présentation du club) | M38: Dîner de membres hors les murs | N38: À qualifier | O38: Vérifier l'activité et l'effectif
A39: Proposition ajoutée | B39: 3. Cercles privés et clubs d'affaires | C39: Conciergeries et clubs de cartes premium (rappel du fichier BtoC) | D39: P2 (proposé) | E39: Prescripteur | F39: Non établi | I39: =IF(H39="","",ROUND(H39*Hypothèses!$B$3,0)) | J39: =IF(H39="","",ROUND(I39/Hypothèses!$B$4,1)) | K39: =IF(H39="","",J39*Hypothèses!$B$7) | M39: Relais vers des particuliers déjà constitués en groupes | N39: À qualifier | O39: Vérifier l'activité et l'effectif

Sheet Hypothèses
A1: Hypothèses du calcul de potentiel (modifiables)
A3: Part des membres qui viendraient à au moins une soirée Pop Tables dans l'année | B3: 0.03 | C3: H, à tester lors des premiers rendez-vous
A4: Jauge d'une privatisation (couverts) | B4: 20 | C4: F cadre Pop Tables, D-05
A5: Forfait de privatisation (€ TTC) | B5: 6000 | C5: F cadre Pop Tables, D-10 (chef confirmé)
A6: Prix par convive en privatisation (€ TTC) | B6: 300 | C6: F cadre Pop Tables, D-10 (chef confirmé)
A7: Chiffre d'affaires d'une privatisation (€ TTC) | B7: =B5+B6*B4 | C7: Calcul

Sheet Sources
A1: Source | B1: Lien | C1: Date
A2: Liste « Démarchage des groupes - Offres événementielles » (dépôt) | B2: 4 VENTES/CLIENTS/2026 1028 Demarchage des groupes - Offres evenementielles.md | C2: 28/10/2026
A3: Cadre de référence Pop Tables (jauges, prix) | B3: 1 DIRECTION/STRATEGIE/2026 1028 Pop Tables - Cadre de référence.md | C3: 28/10/2026
A4: Wikipédia, Club des Cent | B4: https://en.wikipedia.org/wiki/Club_des_Cent | C4: consulté le 28/10/2026
A5: Chaîne des Rôtisseurs France (≈ 25 000 membres) | B5: https://france.chainedesrotisseurs.com/ | C5: consulté le 28/10/2026
A6: Pépites, le club des 1000 | B6: https://rejoindre.pepites-club.com/ | C6: consulté le 28/10/2026
A7: Paris Zigzag, Pépites | B7: https://www.pariszigzag.fr/insolite/balades-excursions/club-pepites/ | C7: non datée
A8: Infrarouge, 7 clubs à Paris pour trouver du réseau (Cookoon, Saint James) | B8: https://www.infrarouge.fr/7-clubs-paris-reseau/ | C8: 2024
A9: Disciples Escoffier (effectifs mondiaux) | B9: https://www.echodumardi.com/actualite/un-nouveau-president-pour-les-disciples-descoffier-de-provence-languedoc/ | C9: 2025
A10: Wikipédia FR, Automobile Club de France | B10: https://fr.wikipedia.org/wiki/Automobile_Club_de_France | C10: consulté le 28/10/2026
A11: Wikipédia, Cercle de l'Union interalliée | B11: https://en.wikipedia.org/wiki/Cercle_de_l%27Union_interalli%C3%A9e | C11: consulté le 28/10/2026
A12: Wikipédia FR, Saint James Paris | B12: https://fr.wikipedia.org/wiki/Saint_James_Paris | C12: consulté le 28/10/2026
... A25: Wikipédia, Club des Croqueurs de Chocolat | B25: https://en.wikipedia.org/wiki/Club_des_Croqueurs_de_Chocolat | C25: consulté le 28/10/2026
