Workbook

Sheet Mode d'emploi
A1: Financement — levées de fonds, prêts, subventions, table de capitalisation
A2: Pop Tables · Pôle Finance · Version du 28/10/2026 (soir). Remplace le modèle du 27/10 (rangé dans 2 FINANCE/OLD).
A4: Rubrique | B4: Contenu
A5: Objet | B5: Suivre les levées de fonds, prêts et subventions, et tenir la table de capitalisation (2 FINANCE/FINANCEMENT/LISEZ-MOI.md).
A6: Onglets | B6: « Suivi des financements » : chaque financement, du projet aux fonds reçus. « Prêts » : mensualités et coût des emprunts. « Table de capitalisation » : la répartition du capital à une date donnée (un état). « Après levée » : la répartition après une levée envisagée (une projection).
A7: Demandé, accordé, reçu | B7: Un montant demandé n'est pas un montant obtenu. Seuls les financements au statut « Fonds reçus » entrent dans le total reçu ; la colonne « Pièce prouvant les fonds reçus » est obligatoire pour ce statut (relevé bancaire, attestation de dépôt des fonds).
A8: Proposition de termes | B8: Une proposition de termes non signée n'est pas une levée réalisée : la noter au statut « Accordé, non signé » tant que les fonds ne sont pas reçus ou les titres émis.
A9: Droits particuliers | B9: Actions de préférence, préférence de liquidation, anti-dilution, BSA ou BSPCE changent ce que chaque associé reçoit : les noter dans la colonne « Droits particuliers » et les lire avant de calculer une part.
A10: Après levée | B10: Une table de capitalisation « après » une levée est une projection, pas un état. L'onglet le rappelle en titre.
A11: Légende des cellules | B11: Cellule jaune, texte bleu : donnée à saisir. Cellule grise : formule, ne pas modifier. Texte vert : valeur reprise d'un autre onglet. Ligne verte « Exemple » : montre le format attendu, à remplacer ou supprimer.
A12: Colonne « Nature » | B12: F = fait constaté dans une pièce citée · I = inférence · P = proposition · H = hypothèse à valider (voir RULES.md). Si la pièce ne dit pas le chiffre : « non établi par les sources ».
A13: Colonne « Source » | B13: La pièce et l'endroit exact (ex. : S04, § Contexte, ou le nom de la note du dépôt). Signaler un chiffre tiré d'un argumentaire (plan d'affaires, présentation) plutôt que d'un document de gestion (facture, relevé, procès-verbal).
A14: Unités | B14: Montants en euros hors taxes, sauf mention contraire. Pourcentages saisis en % (ex. : 15 %).
A15: Cadre du projet | B15: Pop Tables (D-02 à D-26). Sources : 1 DIRECTION/STRATEGIE/2026 1028 Pop Tables - Cadre de référence, Business Model Canvas V6 (D-24) et relevé du 29/10 (matin).
... A17: État du fichier | B17: Mis à jour le 29/10/2026 : SAS au capital de 70 000 €, apporté à parts égales par les 7 fondateurs (D-26, forme précisée par le responsable Finance) ; pas de BSA AIR ; complément de 45 000 € à décider (prêt bancaire ou apport complémentaire) ; tranche 2 conditionnelle en augmentation de capital ; associé gastronomique en apport en industrie (D-17). Aucun financement reçu ; tout reste au statut « Envisagé ».

Sheet Suivi des financements
A1: Suivi des financements
A2: Un financement par ligne, mis à jour à chaque changement de statut. Désigner une personne extérieure par son rôle entre crochets.
A4: N° | B4: Type | C4: Financeur (organisme ou rôle) | D4: Date de la demande | E4: Montant demandé (€) | F4: Statut | G4: Montant accordé (€) | H4: Montant reçu (€) | I4: Date de réception | J4: Pièce prouvant les fonds reçus | K4: Conditions (taux, durée, contreparties) | L4: Nature | M4: Source | N4: Remarques
A5: Ex. | B5: Prêt d'honneur | C5: [réseau d'accompagnement] | D5: jj/mm/aaaa | E5: montant en € | F5: Envisagé | K5: à préciser | L5: H | M5: Note du dépôt où la piste est décrite | N5: Ligne d'exemple : à remplacer
A6: 1 | B6: Apport des associés | C6: [7 fondateurs, à parts égales : 10 000 € chacun] | E6: 70000 | F6: Envisagé | K6: Capital initial de la SAS à sa création (novembre 2026) ; précise D-26 (mise de fonds de 70 000 €) : apport en capital des fondateurs, pas de BSA AIR. Aucun fonds versé | L6: P | M6: Choix du responsable Finance (29/10/2026) ; 1 DIRECTION/STRATEGIE/2026 1029 Relevé de décisions du 29 octobre (matin), D-26
A7: 2 | B7: Prêt d'honneur | C7: [réseau d'accompagnement à la création] | E7: 20000 | F7: Envisagé | K7: Prêt personnel aux fondateurs, taux zéro, 5 ans (H) | L7: H | M7: Hypothèse temporaire ; couvre le besoin de l'année 1 du plan financier (2 FINANCE/PREVISIONS)
A8: 3 | B8: Subvention | C8: [concours ou incubateur] | E8: 5000 | F8: Envisagé | K8: À identifier | L8: H | M8: Hypothèse temporaire ; aucun dispositif identifié dans le dépôt
A9: 4 | B9: Autre | C9: [à décider : prêt bancaire ou apport complémentaire des fondateurs] | E9: 45000 | F9: Envisagé | K9: Complément de la réserve de l'année 1 (contingence et trésorerie de sécurité) ; remplace les 45 000 € de BSA AIR. Source à décider par la Direction | L9: P | M9: 2 FINANCE/FINANCEMENT/2026 1028 Note pour décision - levée de fonds Pop Tables, § 5 et 6
A10: 5 | B10: Levée de fonds | C10: [augmentation de capital, investisseurs à identifier] | E10: 0 | F10: Envisagé | K10: Tranche 2 conditionnelle (D-23) : non nécessaire dans le plan ; à décider en mai 2028 au vu des privatisations constatées. Environ 215 000 € si elles restent proches de 8 par ville et par an (note, § 4) | L10: P | M10: Idem
A11: 6 | B11: Apport des associés | C11: [associé gastronomique, à identifier] | E11: 0 | F11: Envisagé | K11: Apport en industrie (D-17) : actions en contrepartie de son réseau, de sa sélection et de son image ; aucune trésorerie ; forme à définir par le Juridique | L11: P | M11: Décision D-17 du 28/10/2026 ; part proposée dans l'onglet « Après levée »
A12: 7
A13: 8
A14: 9
A15: 10
A16: 11
A17: 12
A18: 13
A19: 14
A20: 15
A21: 16
A22: 17
A23: 18
... A25: 20
A27: Totaux (calculés)
B28: Total demandé (hors refusés) | E28: =SUMIFS(E6:E25,F6:F25,"<>Refusé") -> 140000
B29: Total accordé ou signé, pas encore reçu | E29: =SUMIFS(G6:G25,F6:F25,"Accordé, non signé")+SUMIFS(G6:G25,F6:F25,"Signé") -> 0
B30: Total reçu (statut « Fonds reçus ») | E30: =SUMIFS(H6:H25,F6:F25,"Fonds reçus") -> 0
B31: Lignes « Fonds reçus » sans pièce justificative | E31: =COUNTIFS(F6:F25,"Fonds reçus",J6:J25,"") -> 0
A33: Par type de financement
B34: Type | C34: Demandé (€, hors refusés) | D34: Reçu (€)
B35: Apport des associés | C35: =SUMIFS($E$6:$E$25,$B$6:$B$25,B35,$F$6:$F$25,"<>Refusé") -> 70000 | D35: =SUMIFS($H$6:$H$25,$B$6:$B$25,B35,$F$6:$F$25,"Fonds reçus") -> 0
B36: Levée de fonds | C36: =SUMIFS($E$6:$E$25,$B$6:$B$25,B36,$F$6:$F$25,"<>Refusé") -> 0 | D36: =SUMIFS($H$6:$H$25,$B$6:$B$25,B36,$F$6:$F$25,"Fonds reçus") -> 0
B37: Prêt bancaire | C37: =SUMIFS($E$6:$E$25,$B$6:$B$25,B37,$F$6:$F$25,"<>Refusé") -> 0 | D37: =SUMIFS($H$6:$H$25,$B$6:$B$25,B37,$F$6:$F$25,"Fonds reçus") -> 0
B38: Prêt d'honneur | C38: =SUMIFS($E$6:$E$25,$B$6:$B$25,B38,$F$6:$F$25,"<>Refusé") -> 20000 | D38: =SUMIFS($H$6:$H$25,$B$6:$B$25,B38,$F$6:$F$25,"Fonds reçus") -> 0
B39: Subvention | C39: =SUMIFS($E$6:$E$25,$B$6:$B$25,B39,$F$6:$F$25,"<>Refusé") -> 5000 | D39: =SUMIFS($H$6:$H$25,$B$6:$B$25,B39,$F$6:$F$25,"Fonds reçus") -> 0
B40: Avance remboursable | C40: =SUMIFS($E$6:$E$25,$B$6:$B$25,B40,$F$6:$F$25,"<>Refusé") -> 0 | D40: =SUMIFS($H$6:$H$25,$B$6:$B$25,B40,$F$6:$F$25,"Fonds reçus") -> 0
B41: Autre | C41: =SUMIFS($E$6:$E$25,$B$6:$B$25,B41,$F$6:$F$25,"<>Refusé") -> 45000 | D41: =SUMIFS($H$6:$H$25,$B$6:$B$25,B41,$F$6:$F$25,"Fonds reçus") -> 0

Sheet Prêts
A1: Prêts et avances remboursables
A2: Un prêt par ligne, reporté du suivi des financements une fois signé. Mensualité calculée à taux fixe, sans différé ni assurance.
A4: N° du suivi | B4: Prêteur | C4: Montant emprunté (€) | D4: Taux annuel (%) | E4: Durée de remboursement (mois) | F4: Mensualité (€) | G4: Coût total des intérêts (€) | H4: Date de la première échéance | I4: Pièce (contrat signé) | J4: Nature | K4: Source
A5: 2 | B5: [réseau d'accompagnement à la création] | C5: 20000 | D5: 0 | E5: 60 | F5: =IF(AND(C5>0,E5>0),IF(D5=0,C5/E5,PMT(D5/12,E5,-C5)),0) -> 333.33333 | G5: =IF(F5>0,F5*E5-C5,0) -> 0 | I5: Aucune : prêt non signé, simulation | J5: H | K5: Hypothèse temporaire (ligne 2 du suivi des financements)
F6: =IF(AND(C6>0,E6>0),IF(D6=0,C6/E6,PMT(D6/12,E6,-C6)),0) -> 0 | G6: =IF(F6>0,F6*E6-C6,0) -> 0
F7: =IF(AND(C7>0,E7>0),IF(D7=0,C7/E7,PMT(D7/12,E7,-C7)),0) -> 0 | G7: =IF(F7>0,F7*E7-C7,0) -> 0
F8: =IF(AND(C8>0,E8>0),IF(D8=0,C8/E8,PMT(D8/12,E8,-C8)),0) -> 0 | G8: =IF(F8>0,F8*E8-C8,0) -> 0
F9: =IF(AND(C9>0,E9>0),IF(D9=0,C9/E9,PMT(D9/12,E9,-C9)),0) -> 0 | G9: =IF(F9>0,F9*E9-C9,0) -> 0
F10: =IF(AND(C10>0,E10>0),IF(D10=0,C10/E10,PMT(D10/12,E10,-C10)),0) -> 0 | G10: =IF(F10>0,F10*E10-C10,0) -> 0
F11: =IF(AND(C11>0,E11>0),IF(D11=0,C11/E11,PMT(D11/12,E11,-C11)),0) -> 0 | G11: =IF(F11>0,F11*E11-C11,0) -> 0
F12: =IF(AND(C12>0,E12>0),IF(D12=0,C12/E12,PMT(D12/12,E12,-C12)),0) -> 0 | G12: =IF(F12>0,F12*E12-C12,0) -> 0
F13: =IF(AND(C13>0,E13>0),IF(D13=0,C13/E13,PMT(D13/12,E13,-C13)),0) -> 0 | G13: =IF(F13>0,F13*E13-C13,0) -> 0
F14: =IF(AND(C14>0,E14>0),IF(D14=0,C14/E14,PMT(D14/12,E14,-C14)),0) -> 0 | G14: =IF(F14>0,F14*E14-C14,0) -> 0
B15: Total | C15: =SUM(C5:C14) -> 20000 | F15: =SUM(F5:F14) -> 333.33333 | G15: =SUM(G5:G14) -> 0
A17: Le total des mensualités est à reporter en décaissement dans le suivi de trésorerie (2 FINANCE/TRESORERIE).

Sheet Table de capitalisation
A1: Table de capitalisation — état à une date
A2: Un état daté, fondé sur une pièce (statuts, registre des mouvements de titres, procès-verbal d'assemblée).
A3: Date de l'état : | B3: 46327 | C3: Pièce : | D3: Aucune : société non créée. Projet : SAS au capital de 70 000 €, 7 fondateurs à parts égales (10 000 actions de 1 € chacun), dont 2 fondateurs exécutifs ; choix du responsable Finance du 29/10/2026, statuts à rédiger par le Juridique
A5: Associé ou porteur (nom ou rôle) | B5: Catégorie de titres | C5: Nombre de titres | D5: % du capital | E5: % totalement dilué | F5: Apport (€) | G5: Date d'entrée | H5: Droits particuliers | I5: Pièce | J5: Nature
A6: Associé fondateur (Direction) | B6: Actions ordinaires | C6: 10000 | D6: =IF(OR(B6="BSA ou BSPCE non exercés",$C$18-$C$19=0),0,C6/($C$18-$C$19)) -> 0.14285714 | E6: =IF($C$18=0,0,C6/$C$18) -> 0.14285714 | F6: 10000 | G6: 46327 | H6: Aucun | I6: Aucune | J6: P
A7: Associé fondateur (Finance) | B7: Actions ordinaires | C7: 10000 | D7: =IF(OR(B7="BSA ou BSPCE non exercés",$C$18-$C$19=0),0,C7/($C$18-$C$19)) -> 0.14285714 | E7: =IF($C$18=0,0,C7/$C$18) -> 0.14285714 | F7: 10000 | G7: 46327 | H7: Aucun | I7: Aucune | J7: P
A8: Associé fondateur (Marketing) | B8: Actions ordinaires | C8: 10000 | D8: =IF(OR(B8="BSA ou BSPCE non exercés",$C$18-$C$19=0),0,C8/($C$18-$C$19)) -> 0.14285714 | E8: =IF($C$18=0,0,C8/$C$18) -> 0.14285714 | F8: 10000 | G8: 46327 | H8: Aucun | I8: Aucune | J8: P
A9: Associé fondateur (Ventes) | B9: Actions ordinaires | C9: 10000 | D9: =IF(OR(B9="BSA ou BSPCE non exercés",$C$18-$C$19=0),0,C9/($C$18-$C$19)) -> 0.14285714 | E9: =IF($C$18=0,0,C9/$C$18) -> 0.14285714 | F9: 10000 | G9: 46327 | H9: Aucun | I9: Aucune | J9: P
A10: Associé fondateur (Produit) | B10: Actions ordinaires | C10: 10000 | D10: =IF(OR(B10="BSA ou BSPCE non exercés",$C$18-$C$19=0),0,C10/($C$18-$C$19)) -> 0.14285714 | E10: =IF($C$18=0,0,C10/$C$18) -> 0.14285714 | F10: 10000 | G10: 46327 | H10: Aucun | I10: Aucune | J10: P
A11: Associé fondateur (Opérations) | B11: Actions ordinaires | C11: 10000 | D11: =IF(OR(B11="BSA ou BSPCE non exercés",$C$18-$C$19=0),0,C11/($C$18-$C$19)) -> 0.14285714 | E11: =IF($C$18=0,0,C11/$C$18) -> 0.14285714 | F11: 10000 | G11: 46327 | H11: Aucun | I11: Aucune | J11: P
A12: Associé fondateur (Juridique) | B12: Actions ordinaires | C12: 10000 | D12: =IF(OR(B12="BSA ou BSPCE non exercés",$C$18-$C$19=0),0,C12/($C$18-$C$19)) -> 0.14285714 | E12: =IF($C$18=0,0,C12/$C$18) -> 0.14285714 | F12: 10000 | G12: 46327 | H12: Aucun | I12: Aucune | J12: P
D13: =IF(OR(B13="BSA ou BSPCE non exercés",$C$18-$C$19=0),0,C13/($C$18-$C$19)) -> 0 | E13: =IF($C$18=0,0,C13/$C$18) -> 0
D14: =IF(OR(B14="BSA ou BSPCE non exercés",$C$18-$C$19=0),0,C14/($C$18-$C$19)) -> 0 | E14: =IF($C$18=0,0,C14/$C$18) -> 0
D15: =IF(OR(B15="BSA ou BSPCE non exercés",$C$18-$C$19=0),0,C15/($C$18-$C$19)) -> 0 | E15: =IF($C$18=0,0,C15/$C$18) -> 0
D16: =IF(OR(B16="BSA ou BSPCE non exercés",$C$18-$C$19=0),0,C16/($C$18-$C$19)) -> 0 | E16: =IF($C$18=0,0,C16/$C$18) -> 0
D17: =IF(OR(B17="BSA ou BSPCE non exercés",$C$18-$C$19=0),0,C17/($C$18-$C$19)) -> 0 | E17: =IF($C$18=0,0,C17/$C$18) -> 0
A18: Total des titres (y compris BSA et BSPCE) | C18: =SUM(C6:C17) -> 70000 | D18: =SUM(D6:D17) -> 1 | E18: =SUM(E6:E17) -> 1 | F18: =SUM(F6:F17) -> 70000
A19: dont BSA ou BSPCE non exercés | C19: =SUMIFS(C6:C17,B6:B17,"BSA ou BSPCE non exercés") -> 0

Sheet Après levée
A1: Après levée : PROJECTION (pas un état)
A2: Simule une levée envisagée à partir de la table de capitalisation. Ne prouve ni l'accord des investisseurs, ni l'émission des titres.
A4: Paramètre | B4: Valeur | C4: Nature | D4: Source
A5: Valorisation avant levée (€) | B5: 400000 | C5: H | D5: H non justifiée : aucune évaluation. Ne sert qu'en cas d'augmentation de capital (tranche 2)
A6: Montant levé (€) | B6: 0 | C6: P | D6: Pas de levée en fonds propres dans le plan : pas de BSA AIR (choix du responsable Finance, 29/10/2026). Une augmentation de capital ne serait envisagée qu'en cas de tranche 2 (décision en mai 2028)
A7: Nom ou rôle du ou des investisseurs | C7: H | D7: 1 DIRECTION/STRATEGIE/2026 1027 Fiche de synthèse du projet, § Associé gastronomique (proposition)
A8: Titres avant levée, totalement dilués (associé gastronomique compris) | B8: ='Table de capitalisation'!C18+B26 -> 73684
A9: Prix par titre (€) | B9: =IF(B8>0,B5/B8,0) -> 5.4285869
A10: Nouveaux titres émis | B10: =IF(B9>0,ROUND(B6/B9,0),0) -> 0
A11: Valorisation après levée (€) | B11: =B5+B6 -> 400000
A12: Part des investisseurs après levée | B12: =IF(B11>0,B6/B11,0) -> 0
A13: Part proposée pour l'associé gastronomique, avant la levée | B13: 0.05 | C13: P | D13: Proposition de la Finance (D-17 : entrée au capital en contrepartie d'un apport non monétaire) ; acquisition par jalons à prévoir par le Juridique
A14: Associé ou porteur | B14: Titres avant | C14: % avant (totalement dilué) | D14: Titres après | E14: % après (totalement dilué)
A15: =IF('Table de capitalisation'!A6="","",'Table de capitalisation'!A6) -> Associé fondateur (Direction) | B15: ='Table de capitalisation'!C6 -> 10000 | C15: =IF($B$8=0,0,B15/$B$8) -> 0.13571467 | D15: =B15 -> 10000 | E15: =IF($D$28=0,0,D15/$D$28) -> 0.13571467
A16: =IF('Table de capitalisation'!A7="","",'Table de capitalisation'!A7) -> Associé fondateur (Finance) | B16: ='Table de capitalisation'!C7 -> 10000 | C16: =IF($B$8=0,0,B16/$B$8) -> 0.13571467 | D16: =B16 -> 10000 | E16: =IF($D$28=0,0,D16/$D$28) -> 0.13571467
A17: =IF('Table de capitalisation'!A8="","",'Table de capitalisation'!A8) -> Associé fondateur (Marketing) | B17: ='Table de capitalisation'!C8 -> 10000 | C17: =IF($B$8=0,0,B17/$B$8) -> 0.13571467 | D17: =B17 -> 10000 | E17: =IF($D$28=0,0,D17/$D$28) -> 0.13571467
A18: =IF('Table de capitalisation'!A9="","",'Table de capitalisation'!A9) -> Associé fondateur (Ventes) | B18: ='Table de capitalisation'!C9 -> 10000 | C18: =IF($B$8=0,0,B18/$B$8) -> 0.13571467 | D18: =B18 -> 10000 | E18: =IF($D$28=0,0,D18/$D$28) -> 0.13571467
A19: =IF('Table de capitalisation'!A10="","",'Table de capitalisation'!A10) -> Associé fondateur (Produit) | B19: ='Table de capitalisation'!C10 -> 10000 | C19: =IF($B$8=0,0,B19/$B$8) -> 0.13571467 | D19: =B19 -> 10000 | E19: =IF($D$28=0,0,D19/$D$28) -> 0.13571467
A20: =IF('Table de capitalisation'!A11="","",'Table de capitalisation'!A11) -> Associé fondateur (Opérations) | B20: ='Table de capitalisation'!C11 -> 10000 | C20: =IF($B$8=0,0,B20/$B$8) -> 0.13571467 | D20: =B20 -> 10000 | E20: =IF($D$28=0,0,D20/$D$28) -> 0.13571467
A21: =IF('Table de capitalisation'!A12="","",'Table de capitalisation'!A12) -> Associé fondateur (Juridique) | B21: ='Table de capitalisation'!C12 -> 10000 | C21: =IF($B$8=0,0,B21/$B$8) -> 0.13571467 | D21: =B21 -> 10000 | E21: =IF($D$28=0,0,D21/$D$28) -> 0.13571467
A22: =IF('Table de capitalisation'!A13="","",'Table de capitalisation'!A13) | B22: ='Table de capitalisation'!C13 -> 0 | C22: =IF($B$8=0,0,B22/$B$8) -> 0 | D22: =B22 -> 0 | E22: =IF($D$28=0,0,D22/$D$28) -> 0
A23: =IF('Table de capitalisation'!A14="","",'Table de capitalisation'!A14) | B23: ='Table de capitalisation'!C14 -> 0 | C23: =IF($B$8=0,0,B23/$B$8) -> 0 | D23: =B23 -> 0 | E23: =IF($D$28=0,0,D23/$D$28) -> 0
A24: =IF('Table de capitalisation'!A15="","",'Table de capitalisation'!A15) | B24: ='Table de capitalisation'!C15 -> 0 | C24: =IF($B$8=0,0,B24/$B$8) -> 0 | D24: =B24 -> 0 | E24: =IF($D$28=0,0,D24/$D$28) -> 0
A25: =IF('Table de capitalisation'!A16="","",'Table de capitalisation'!A16) | B25: ='Table de capitalisation'!C16 -> 0 | C25: =IF($B$8=0,0,B25/$B$8) -> 0 | D25: =B25 -> 0 | E25: =IF($D$28=0,0,D25/$D$28) -> 0
A26: Associé gastronomique (apport en industrie, D-17) | B26: =ROUND('Table de capitalisation'!C18*B13/(1-B13),0) -> 3684 | C26: =IF($B$8=0,0,B26/$B$8) -> 0.049997286 | D26: =B26 -> 3684 | E26: =IF($D$28=0,0,D26/$D$28) -> 0.049997286
A27: =IF(B7="","Nouveaux investisseurs",B7) -> Nouveaux investisseurs | B27: 0 | C27: 0 | D27: =B10 -> 0 | E27: =IF($D$28=0,0,D27/$D$28) -> 0
A28: Total | B28: =SUM(B15:B27) -> 73684 | C28: =SUM(C15:C27) -> 1 | D28: =SUM(D15:D27) -> 73684 | E28: =SUM(E15:E27) -> 1
A30: Non modélisé : préférence de liquidation, anti-dilution, création d'un nouveau plan de BSPCE. Les lire dans les pièces avant de calculer ce que chaque associé reçoit.
